Workbook

Sheet Introductory notes and summary
A1: Scores | B1: Description | C1: N° of papers | D1: Available | E1: Screening | G1: ToT papers | H1: Discarded | I1: Selected | J1: ToT Eligible | M1: Scores | N1: Description | O1: N° of papers Eligible | P1: Discarded | Q1: Included | R1: Eligibility | U1: Eligible papers | V1: Included papers
A2: 1 | B2: Papers focused on examples or approaches or method of cyber-attacks (DDOS, jamming, spoofing, etc) in AAM. These papers provide at least an introduction on cyberattacks in AAM. | C2: =COUNTIF(Selected_papers!B:B,"1") -> 152 | D2: =COUNTIFS(Selected_papers!A:A, "Y",Selected_papers!B:B, 1) -> 134 | G2: =COUNTIF(Selected_papers!C:C,"Y")+COUNTIF(Selected_papers!C:C,"N") -> 736 | H2: =COUNTIF(Selected_papers!C:C,"N") -> 487 | I2: =COUNTIF(Selected_papers!C:C,"Y") -> 249 | J2: =COUNTIF(Selected_papers!A:A,"Y") -> 224 | M2: 1 | N2: Papers focused on examples or approaches or method of cyber-attacks (DDOS, jamming, spoofing, etc) in AAM. These papers provide at least an introduction on cyberattacks in AAM. | O2: =D2 -> 134 | P2: =COUNTIFS(#REF!, "Y",#REF!, 1) -> #REF! | Q2: =O2-P2 -> #REF! | U2: =SUM(O2:O12) -> 224 | V2: =SUM(Q2:Q4) -> #REF!
A3: 2 | B3: Papers focused on Cyber-resilience & AAM: taxonomy of cyber-attacks, countermeasures, recommendations, safety and resilience perspective. | C3: =COUNTIF(Selected_papers!B:B,"2") -> 67 | D3: =COUNTIFS(Selected_papers!A:A, "Y",Selected_papers!B:B, 2) -> 60 | G3: Identification | H3: Screening | J3: Start Eligibility | M3: 2 | N3: Papers focused on Cyber-resilience & AAM: taxonomy of cyber-attacks, countermeasures, recommendations, safety and resilience perspective. | O3: =D3 -> 60 | P3: =COUNTIFS(#REF!, "Y",#REF!, 2) -> #REF! | Q3: =O3-P3 -> #REF!
A4: 3 | B4: Papers focused on Cyber-resilience & AAM: Literature review and surveys | C4: =COUNTIF(Selected_papers!B:B,"3") -> 30 | D4: =COUNTIFS(Selected_papers!A:A, "Y",Selected_papers!B:B, 3) -> 30 | J4: Total available | M4: 3 | N4: Papers focused on Cyber-resilience & AAM: Literature review and surveys | O4: =D4 -> 30 | P4: =COUNTIFS(#REF!, "Y",#REF!, 3) -> #REF! | Q4: =O4-P4 -> #REF!
A5: N0 | B5: Out of scope 0: technical publications that cover cybersecurity, communication, robust protocols, integrated network, blockchain, and other approaches to defending or addressing cyber-attacks in aviation or AAM. | C5: =COUNTIF(Selected_papers!B:B,"N0") -> 211 | D5: NA
A6: N1 | B6: Out of scope 1: papers on UAVs operations to monitoring, inspections, identification, assessment (industrial plants, agricolture, pipeline,wildlife,…) | C6: =COUNTIF(Selected_papers!B:B,"N1") -> 64 | D6: NA
A7: N2 | B7: Out of scope 2: papers focused on enhancing or adding new AAM/UAV features (Positioning through GPS, security, communication, flight mechanics, image acquisition, detection, antennas interference), other operational use. | C7: =COUNTIF(Selected_papers!B:B,"N2") -> 143 | D7: NA
A8: N3 | B8: Out of scope 3: papers on enhancing or adding new features applying neural network, AI, blockchain, machine learning algorithm, with little to none focus on cybersecurity, cyber-resilience, AAM, drones. | C8: =COUNTIF(Selected_papers!B:B,"N3") -> 20 | D8: NA
A9: N4 | B9: Out of scope 4: paper focused on different topic than AAM & Cybersecurity, completely out of scope | C9: =COUNTIF(Selected_papers!B:B,"N4") -> 18 | D9: NA
A10: D1 | B10: Discarded: type of document | C10: =COUNTIF(Selected_papers!B:B,"D1") -> 31 | D10: NA
A11: Duplicate | B11: Duplicates paper from the advanced search | D11: NA
C12: =SUM(C2:C11) -> 736 | D12: =SUM(D2:D4) -> 224

Sheet Scopus_Export
A1: Authors | B1: Author full names | C1: Author(s) ID | D1: Title | E1: Year | F1: Source title | G1: Volume | H1: Issue | I1: Art. No. | J1: Page start | K1: Page end | L1: Page count | M1: DOI | N1: Link | O1: Abstract | P1: Author Keywords | Q1: EID
A2: Novák A.; Kováčiková K.; Kandera B.; Sedláčková A.N. | B2: Novák, Andrej (9241050100); Kováčiková, Kristína (57226781703); Kandera, Branislav (57204831935); Sedláčková, Alena Novák (57842588600) | C2: 9241050100; 57226781703; 57204831935; 57842588600 | D2: Global Navigation Satellite Systems Signal Vulnerabilities in Unmanned Aerial Vehicle Operations: Impact of Affordable Software-Defined Radio | E2: 2024 | F2: Drones | G2: 8 | H2: 3 | I2: 109 | M2: 10.3390/drones8030109 | N2: https://www.scopus.com/inward/record.uri?eid=2-s2.0-85188723814&doi=10.3390%2fdrones8030109&partnerID=40&md5=736173188b2ac7aaf540895e18e677ad | O2: Spoofing, alongside jamming of the Global Navigation Satellite System signal, remains a significant hazard during general aviation or Unmanned Aerial Vehicle operations. As aircraft utilize various support systems for navigation, such as INS, an insufficient Global Navigation Satellite System signal renders Unmanned Aerial Vehicles nearly uncontrollable, thereby posing increased danger to operations within airspace and to individuals on the ground. This paper primarily focuses on assessing the impact of the budget friendly Software-Defined Radio, HackRF One 1.0, on the safety of Unmanned Aerial Vehicles operations. Considering the widespread use of Software-Defined Radio devices today, with some being reasonably inexpensive, understanding their influence on Unmanned Aerial Vehicles safety is crucial. The generation of artificial interference capable of posing a potential threat in expanding Unmanned Aerial Vehicles airspace is deemed unacceptable. © 2024 by the authors. | P2: GNSS; interference; jamming; UAV | Q2: 2-s2.0-85188723814
A3: Vélez S.; Ariza-Sentís M.; Panić M.; Ivošević B.; Stefanović D.; Kaivosoja J.; Valente J. | B3: Vélez, Sergio (57215185725); Ariza-Sentís, Mar (56964491300); Panić, Marko (33368184800); Ivošević, Bojana (56538600400); Stefanović, Dimitrije (58038387300); Kaivosoja, Jere (49861371000); Valente, João (42062501000) | C3: 57215185725; 56964491300; 33368184800; 56538600400; 58038387300; 49861371000; 42062501000 | D3: Speeding up UAV-based crop variability assessment through a data fusion approach using spatial interpolation for site-specific management | E3: 2024 | F3: Smart Agricultural Technology | G3: 8 | I3: 100488 | M3: 10.1016/j.atech.2024.100488 | N3: https://www.scopus.com/inward/record.uri?eid=2-s2.0-85196262805&doi=10.1016%2fj.atech.2024.100488&partnerID=40&md5=a1e1d2616c40f33c73617841adf84c71 | O3: Innovations in precision agriculture enhance complex tasks, reduce environmental impact, and increase food production and cost efficiency. One of the main challenges is ensuring rapid information availability for autonomous vehicles and standardizing processes across platforms to maximize interoperability. The lack of drone technology standardisation, communication barriers, high costs, and post-processing requirements sometimes hinder their widespread use in agriculture. This research introduces a standardized data fusion framework for creating real-time spatial variability maps using images from different Unmanned Aerial Vehicles (UAVs) for Site-Specific Crop Management (SSM). Two spatial interpolation methods were used (Inverse Distance Weight, IDW, and Triangulated Irregular Networks, TIN), selected for their computational efficiency and input flexibility. The proposed framework can use different UAV image sources and offers versatility, speed, and efficiency, consuming up to 98 % less time, energy, and computing requirements than standard photogrammetry techniques, providing rapid field information, allowing edge computing incorporation into the UAV data acquisition phase. Experiments conducted in Spain, Serbia, and Finland in 2022 under the H2020 FlexiGroBots project demonstrated a strong correlation between results from this method and those from standard photogrammetry techniques (up to r = 0.93). In addition, the correlation with Sentinel 2 satellite images was as strong as that obtained with photogrammetry-based orthomosaics (up to r = 0.8). The proposed approach could support irrigation leak detection, soil parameter estimation, weed management, and satellite integration for agriculture. © 2024 The Author(s) | P3: IDW; Precision agriculture; Remote sensing; Satellite; Spatial variability; TIN | Q3: 2-s2.0-85196262805
A4: Periyasami K.; Katina P.F.; Ramasamy R. | B4: Periyasami, Karthikeyan (59279792400); Katina, Polinpapilinho F. (39361629100); Ramasamy, Rajagopal (57254725400) | C4: 59279792400; 39361629100; 57254725400 | D4: Cyber Space and Outer Space Security | E4: 2024 | F4: Cyber Space and Outer Space Security | J4: 1 | K4: 266 | L4: 265 | N4: https://www.scopus.com/inward/record.uri?eid=2-s2.0-85201595905&partnerID=40&md5=2cf1d4dfc5c4c6f559fbff91c9e0c7be | O4: This book delves into cutting-edge research in cyberspace and outer space security, encompassing both theoretical and experimental aspects. It provides mitigation measures and strategies to address the identified challenges within. It covers a spectrum of topics including techniques and strategies for enhancing cyberspace security, combating ransomware attacks, and securing autonomous vehicles. Additionally, it explores security and surveillance systems involving autonomous vehicles, resilience schemes against security attacks using blockchain for autonomous vehicles, security analysis of autonomous drones (UAVs), the cybersecurity kill chain, the internet of drones (IoD), and cyberspace solutions to counteract attacks. The discussion extends to mitigation strategies against weaponized AI in cyber-attacks, countermeasures for both autonomous vehicles and cyberspace attacks, as well as the limitations and future prospects of artificial intelligence (AI) and data defense in aerospace cybersecurity. A network comprising nodes can establish both cyberspace and outer space platforms for data exchange. Cyberspace finds diverse applications, including commercial endeavors and military defense. The integration of autonomous vehicles, unmanned aircraft systems (UAS), and drones into outer space environments is facilitated through their connection to cyberspace. One illustrative example involves the utilization of blockchain-based secure drone systems for product delivery, leveraging the combined capabilities of cyberspace and outer space security technologies. This book elucidates the intricate dynamics between cyber operations and the expanding realm of autonomous outer cyberspace, presenting new security challenges arising from heightened complexity and emerging vulnerabilities. © 2024 River Publishers. All rights reserved. | Q4: 2-s2.0-85201595905
A5: Guo D.; Tang L.; Zhang X.; Liang Y.-C. | B5: Guo, Delin (57215897646); Tang, Lan (35504073000); Zhang, Xinggan (7410277485); Liang, Ying-Chang (36071330300) | C5: 57215897646; 35504073000; 7410277485; 36071330300 | D5: Joint Optimization of Trajectory and Jamming Power for Multiple UAV-Aided Proactive Eavesdropping | E5: 2024 | F5: IEEE Transactions on Mobile Computing | G5: 23 | H5: 5 | I5: 10238835 | J5: 5770 | K5: 5785 | L5: 15 | M5: 10.1109/TMC.2023.3311484 | N5: https://www.scopus.com/inward/record.uri?eid=2-s2.0-85171565918&doi=10.1109%2fTMC.2023.3311484&partnerID=40&md5=9dc452d4a3e8dc2ea012068292ac3409 | O5: This paper studies a novel wireless information surveillance scenario, where the legitimate party aims to eavesdrop on multiple suspicious communication links with the help of multiple unmanned aerial vehicles (UAVs). Each suspicious link is comprised of a UAV (transmitter) and its fixed destination. To improve the eavesdropping ability, cooperative legitimate UAVs emit jamming signals to reduce the capacities of suspicious channels and plan the flight trajectory to enhance the capacity of the eavesdropping channels. Considering the system dynamics, it is natural to model this sequential decision-making problem as a Markov Decision Process (MDP), which might be solved by reinforcement learning (RL). However, it is difficult to design a policy in RL that determines jamming powers satisfying the considered eavesdropping constraints. Therefore, we decompose the optimization process into two phases, 1) obtaining the non-learning-based optimal solver for jamming power allocation under each state, and 2) optimizing the policy of moving action by RL. We will show this decoupled optimization process also holds the optimality. Considering the flying safety, we will determine the individual moving policy for each legitimate UAV rather than a centralized policy that controls all UAVs. Finally, extensive simulations are conducted to demonstrate the effectiveness of the proposed solution. © 2023 IEEE. | P5: power allocation; Proactive eavesdropping; reinforcement learning (RL); trajectory planning; unmanned aerial vehicles (UAVs) | Q5: 2-s2.0-85171565918
A6: Hu M.; Yan X.; Qiu M.; Zhang P.; Wang S. | B6: Hu, Manman (59144293500); Yan, Xiao (58000704500); Qiu, Mingjie (58599992300); Zhang, Peng (58787459400); Wang, Shengli (54992019700) | C6: 59144293500; 58000704500; 58599992300; 58787459400; 54992019700 | D6: Interference Resource Allocation Method Based on Constrained Reinforcement Learning | E6: 2024 | F6: Proceedings of SPIE - The International Society for Optical Engineering | G6: 13283 | I6: 1328340 | M6: 10.1117/12.3037194 | N6: https://www.scopus.com/inward/record.uri?eid=2-s2.0-85212823571&doi=10.1117%2f12.3037194&partnerID=40&md5=c1ff7e4f34130e8989d86f0ee9f5d90e | O6: In modern manned-unmanned cooperative flight formations confronting advanced ground-based radar networks, traditional UAV swarm jamming strategies rely heavily on centralized command from fixed nodes. This centralization, while optimizing decision quality through global situational awareness, also introduces significant vulnerabilities. Dependence on a single node makes the system prone to failure in high-intensity and uncertain environments. Additionally, UAV platform constraints, such as limited power, sensing range, and communication bandwidth, challenge the feasibility of centralized information processing across the entire network. To address these issues, this study presents a decentralized decision-making framework, incorporating an adaptive cluster jamming resource allocation strategy based on collaborative multi-agent reinforcement learning. The Actor-Critic (AC) algorithm is employed to enable autonomous behavior analysis of UAV swarms via policy networks, while a value network is utilized to evaluate and guide policy iterations. The simulation results showed an interference mode allocation result of 20 drones interfering with 3 radars, verifying the possibility of this strategy working in complex dynamic environments. © 2024 SPIE. | P6: Distributed Decision-Making Framework; Multi-Agent Reinforcement Learning; Unmanned Aerial Vehicles (UAVs) | Q6: 2-s2.0-85212823571
A7: Alharthi R. | B7: Alharthi, Raed (57203659754) | C7: 57203659754 | D7: Enhancing unmanned aerial vehicle and smart grid communication security using a ConvLSTM model for intrusion detection | E7: 2024 | F7: Frontiers in Energy Research | G7: 12 | I7: 1491332 | M7: 10.3389/fenrg.2024.1491332 | N7: https://www.scopus.com/inward/record.uri?eid=2-s2.0-85212753771&doi=10.3389%2ffenrg.2024.1491332&partnerID=40&md5=b6ba95c0928536816d94e84406a7688e | O7: The emergence of small-drone technology has revolutionized the way we use drones. Small drones leverage the Internet of Things (IoT) to deliver location-based navigation services, making them versatile tools for various applications. Unmanned aerial vehicle (UAV) communication networks and smart grid communication protocols share several similarities, particularly in terms of their architecture, the nature of the data they handle, and the security challenges they face. To ensure the safe, secure, and reliable operation of both, it is imperative to establish a secure and dependable network infrastructure and to develop and implement robust security and privacy mechanisms tailored to the specific needs of this domain. The research evaluates the performance of deep learning models, including convolutional neural networks (CNN), long short-term memory (LSTM), CNN-LSTM, and convolutional long short-term memory (ConvLSTM), in detecting intrusions within UAV communication networks. The study utilizes five diverse and realistic datasets, namely, KDD Cup-99, NSL-KDD, WSN-DS, CICIDS 2017, and Drone, to simulate real-world intrusion scenarios. Notably, the ConvLSTM model consistently achieves an accuracy of 99.99%, showcasing its potential in securing UAVs from cyber threats. By demonstrating its superior performance, this work highlights the importance of tailored security mechanisms in safeguarding UAV technology against evolving cyber threats. Ultimately, this research contributes to the growing body of knowledge on UAV security, emphasizing the necessity of high-quality datasets and advanced models in ensuring the safe, secure, and reliable operation of UAV systems across various industries. Copyright © 2024 Alharthi. | P7: communication security; cyber resilience; intrusion detection; smart grid; unmanned aerial vehicles | Q7: 2-s2.0-85212753771
A8: Basak S.; Rajendran S.; Pollin S.; Scheers B. | B8: Basak, Sanjoy (57191051079); Rajendran, Sreeraj (57191669277); Pollin, Sofie (8601601500); Scheers, Bart (23478501400) | C8: 57191051079; 57191669277; 8601601500; 23478501400 | D8: Spectrum Prediction for Protocol-Aware RF Jamming | E8: 2024 | F8: IEEE Transactions on Cognitive Communications and Networking | G8: 10 | H8: 2 | J8: 363 | K8: 373 | L8: 10 | M8: 10.1109/TCCN.2023.3327538 | N8: https://www.scopus.com/inward/record.uri?eid=2-s2.0-85176301898&doi=10.1109%2fTCCN.2023.3327538&partnerID=40&md5=7fa595e799408171cafd4d9ba0cf5e40 | O8: Neutralizing a drone using a protocol-aware RF jammer requires precise knowledge of the occupied spectrum in the time and frequency domains. This paper aims to develop an automatic spectrum prediction framework utilizing the Convolutional Neural Network (CNN) and Long Short Term Memory (LSTM) models. We generate a synthetic dataset using the commonly used drone signal properties and parameters, and evaluate the prediction performance under several realistic scenarios. Our experiment shows that the CNN-LSTM model can accurately predict future time and frequency sequences by using the spectrogram matrix as the input. We obtained better prediction performance with lower computational costs with our framework compared to the existing frameworks. Furthermore, we show that the CNN-LSTM model can predict future time-frequency sequences of unseen hopping rates and patterns when using transfer learning. The performance validation is also performed using real drone RF signals. Furthermore, we present a two-stage spectrum prediction approach that achieves excellent performance by offering higher frequency resolutions while maintaining a lower computational cost. © 2015 IEEE. | P8: Deep learning; spectrum prediction; UAVs | Q8: 2-s2.0-85176301898
A9: Kumar N.; Chaudhary A. | B9: Kumar, Naveen (59253135800); Chaudhary, Ankit (36600087600) | C9: 59253135800; 36600087600 | D9: Surveying cybersecurity vulnerabilities and countermeasures for enhancing UAV security | E9: 2024 | F9: Computer Networks | G9: 252 | I9: 110695 | M9: 10.1016/j.comnet.2024.110695 | N9: https://www.scopus.com/inward/record.uri?eid=2-s2.0-85200806532&doi=10.1016%2fj.comnet.2024.110695&partnerID=40&md5=b9ac0c4a03c15f1d66aefbbd47166ef1 | O9: Drones and other forms of Unmanned Aerial Vehicles (UAVs) usages are increasing with time from military operations like surveillance, reconnaissance to commercial operations such as transportation, agriculture. The Drone market will be grown to around 43 billion USD by the 2025. With the increase in the usages, there is increase in cyber-attacks. So, Drone security and privacy are of major concern as they are used to perform the critical operations. The rapid adoption of UAVs in various sectors has prompted the need for robust and comprehensive cyber security measures. By implementing robust countermeasures, such as authentication, encryption etc. the risks posed by cyber threats can be significantly mitigated. The study investigates cyber security vulnerabilities and countermeasures in UAV systems within the scope of Authentication techniques, Physical Layer Security, Covert Communication. Relaying and Trajectory Optimization techniques are also discussed so that the flight trajectory can be optimized. It also discusses the communication modes used in UAV communication. An analysis of communication protocols is also carried out in this survey. The goal of the survey is to get the idea of cyber security threats involved in UAV communication. Our analysis emphasizes the importance of a holistic approach to UAV cyber security, leveraging the synergies among these domains to enhance overall resilience. © 2024 Elsevier B.V. | P9: Authentication; Covert communication; Cryptography; Cyber-attacks; GCS; Physical layer security; Relaying; Trajectory optimization; UAV | Q9: 2-s2.0-85200806532
A10: Liu Z.; Zhu B.; Xie Y.; Ma K.; Guan X. | B10: Liu, Zhixin (55714815900); Zhu, Ben (58796416200); Xie, Yuanai (57325394200); Ma, Kai (36650969700); Guan, Xinping (57392292000) | C10: 55714815900; 58796416200; 57325394200; 36650969700; 57392292000 | D10: UAV-Aided Secure Communication With Imperfect Eavesdropper Location: Robust Design for Jamming Power and Trajectory | E10: 2024 | F10: IEEE Transactions on Vehicular Technology | G10: 73 | H10: 5 | J10: 7276 | K10: 7286 | L10: 10 | M10: 10.1109/TVT.2023.3347769 | N10: https://www.scopus.com/inward/record.uri?eid=2-s2.0-85181572608&doi=10.1109%2fTVT.2023.3347769&partnerID=40&md5=0ffc3036a4f824d4629aa556876b17a5 | O10: This paper exploits the mobility of an unmanned aerial vehicle (UAV) to improve the physical layer (PLS) security against potential eavesdropping scenarios, where the sensitive data transmitted from a ground base station (GBS) to multiple information receivers (IRs) is easily eavesdropped by multiple non-colluding eavesdroppers (Eves). Specifically, the UAV is employed as a friendly jammer to transmit artificial noise to degrade the wiretap channels. By leveraging the UAV's mobility and the possibility of establishing line-of-sight links, the UAV can move close to the Eves and opportunistically jam them. Especially, two practical factors, namely, the imperfect location information of Eves and the existence of no-fly zones are considered. Since only the partial position information of the Eves can be known, as the worst case, the minimum average secrecy rate of IRs is robustly optimized by jointly designing the trajectory and jamming power of the UAV, and the transmission power of the GBS to ensure the security of all IRs. However, the formulated problem with coupled variables is non-convex and intractable. As such, an efficient alternative iterative suboptimal algorithm is proposed to solve this problem by applying the block coordinate descent, successive convex approximation, slack variables, and mathcal {S}-Procedure. Numerical results reveal that the proposed robust algorithm can substantially improve the max-min average secrecy rate, and the effectiveness of the proposed algorithm is further verified by comparing it with three benchmark schemes. © 1967-2012 IEEE. | P10: no-fly-zone; physical layer security; robust design; trajectory optimization; transmit power optimization; UAV-adied communication | Q10: 2-s2.0-85181572608
A11: Gupta S.K.; Kumar M.; Nayyar A.; Mahajan S. | B11: Gupta, Sachin Kumar (57213337960); Kumar, Manoj (59315839100); Nayyar, Anand (55201442200); Mahajan, Shubham (57209224750) | C11: 57213337960; 59315839100; 55201442200; 57209224750 | D11: Unmanned Aircraft Systems | E11: 2024 | F11: Unmanned Aircraft Systems | J11: 1 | K11: 653 | L11: 652 | M11: 10.1002/9781394230648 | N11: https://www.scopus.com/inward/record.uri?eid=2-s2.0-85213776471&doi=10.1002%2f9781394230648&partnerID=40&md5=7d85f7ff56c8353d7c530259fa997e81 | O11: This book is an essential resource for anyone looking to understand the cutting-edge applications and evolving technologies of Unmanned Aerial Systems, showcasing how they enhance safety and efficiency in monitoring, emergency response, and smart city development. With the evolution of Unmanned Aircraft Systems (UAS), its applications can be observed in the fields of monitoring for fire detection, sustainable computing, emergencies, and law enforcement. They can be useful for monitoring or screening applications, as well as the deployment of smart cities, security monitoring, and communication establishments at rare locations or unapproachable locations. Thus, the wireless ad-hoc networks of Unmanned Aerial Vehicles (UAVs) and infrastructure-based UAVs can be utilized in this proposal. Unmanned aircraft systems (UAS) extend human potential and allow us to execute dangerous or difficult tasks safely and efficiently, saving time, money, and, most importantly, lives. UAS can help police, fire, and other public workers save lives in emergencies like natural disasters, locate missing animals and children, or help fight fighters. Unmanned Aircraft Systems contains novel contributions and emerging trends in the area of Unmanned Aerial Vehicles (UAV), drones, and aircraft without a human pilot aboard. It has three segments incorporating technological advancements and future trends in UAS, the policies and security aspects of UAVs, and their applications as an intelligent system. Along with these state-of-the-art techniques, this book also incorporates advances in AI and machine learning, deep learning, IoT technology, cybersecurity and Blockchain, UAV regulation policies in the United States and Europe, SOTA in ITS, and many more technological advancements, which makes this book the pioneer and benchmarking reference in these areas. © 2025 Scrivener Publishing LLC. | Q11: 2-s2.0-85213776471
A12: Lu F.; Liu G.; Lu W.; Gao Y.; Cao J.; Zhao N.; Nallanathan A. | B12: Lu, Fangwei (57216841914); Liu, Gongliang (15065645300); Lu, Weidang (59454513400); Gao, Yuan (57113859700); Cao, Jiang (57215003444); Zhao, Nan (45562028800); Nallanathan, Arumugam (6603561059) | C12: 57216841914; 15065645300; 59454513400; 57113859700; 57215003444; 45562028800; 6603561059 | D12: Resource and Trajectory Optimization for UAV-Relay-Assisted Secure Maritime MEC | E12: 2024 | F12: IEEE Transactions on Communications | G12: 72 | H12: 3 | J12: 1641 | K12: 1652 | L12: 11 | M12: 10.1109/TCOMM.2023.3330884 | N12: https://www.scopus.com/inward/record.uri?eid=2-s2.0-85177032462&doi=10.1109%2fTCOMM.2023.3330884&partnerID=40&md5=6f90332308c96404c39e8780bf774c73 | O12: With the evolutional development of maritime networks, the explosive growth of maritime data has put forward elevated demands for the computing capabilities of maritime devices (MDs). Unmanned aerial vehicle (UAV) is able to alleviate the computing pressure of MDs by forwarding the computing tasks to the edge server on the coast. However, UAV relaying introduces a significant security challenge due to the vulnerability of line-of-sight (LoS) communication channels, which can be exploited for eavesdropping on computing tasks. In this paper, an efficient secure communication scheme is proposed for UAV-relay-assisted maritime mobile edge computing (MEC) with a flying eavesdropper. The secure computing capacity of MDs is maximized by jointly optimizing the transmit power, time slot allocation factor, computation optimization and UAV trajectory. Due to multi-variable coupling, the formulated optimization problem (OP) is non-convex. We first transform OP by introducing auxiliary variables. Then, the transformed OP is decomposed and solved in an iterative manner by applying block coordinate descent (BCD) and successive convex approximation (SCA). Numerical results show that the secure computing capability of the UAV-relay-assisted maritime MEC system of proposed secure communication scheme can be effectively improved compared with benchmarks. © 1972-2012 IEEE. | P12: maritime communications; MEC; Secure transmission; UAV-relay | Q12: 2-s2.0-85177032462
A13: Choi S.; Lee J.; Park B.; Jo J. | B13: Choi, Seungho (56889987900); Lee, Junghoon (56545183700); Park, Byungkoo (16639040400); Jo, Jeil (57202046191) | C13: 56889987900; 56545183700; 16639040400; 57202046191 | D13: Implementation and Validation of a Real-time Spoofing System | E13: 2024 | F13: 2024 21st European Radar Conference, EuRAD 2024 | J13: 252 | K13: 255 | L13: 3 | M13: 10.23919/EuRAD61604.2024.10734883 | N13: https://www.scopus.com/inward/record.uri?eid=2-s2.0-85210863711&doi=10.23919%2fEuRAD61604.2024.10734883&partnerID=40&md5=599a5368e2cdaa9dde477a71c8cf6cc8 | O13: Satellite navigation deception, also known as spoof jamming technology, is crucial as an anti-drone technology being developed alongside the revitalization of the drone industry. Unlike existing simulator-type or non-real-time signal generators, this advanced drone jamming technology combines a spoofing deception signal generator with real-time target information and navigation satellite orbit data. In this study, we outlined the design, manufacturing results, and core real time performance metrics, including time and navigation message synchronization. To validate the possibility of directional guidance of an autonomous UAV through spoofing techniques, we developed a novel deception procedure and successfully demonstrated its effectiveness in controlling the flight direction of an autonomous UAV through spoof jamming. © 2024 European Microwave Association (EuMA). | P13: anti-drone; counter-measuring UAV; GNSS spoofing | Q13: 2-s2.0-85210863711
A14: Belfadel D.; Haessig D. | B14: Belfadel, Djedjiga (55915134800); Haessig, David (59389740600) | C14: 55915134800; 59389740600 | D14: Optical Flow for Drone Horizontal Velocity Estimation without GPS | E14: 2024 | F14: FUSION 2024 - 27th International Conference on Information Fusion | M14: 10.23919/FUSION59988.2024.10706252 | N14: https://www.scopus.com/inward/record.uri?eid=2-s2.0-85207692634&doi=10.23919%2fFUSION59988.2024.10706252&partnerID=40&md5=d4382b7bec95ffe88fdcfcbfcc42307b | O14: Unmanned aerial vehicles (UAVs) are widely used in military and civilian applications, such as surveillance, disaster monitoring, and rescue missions. They rely heavily on global positioning systems (GPS) for navigation. However, the accuracy and availability of GPS positioning, navigation, and timing (PNT) data can suffer losses due to jamming and spoofing. To address overreliance on GPS infrastructure, this paper presents a vision-aided system to enable UAVs to estimate velocity and continue operation when GPS signal is intermittently lost. The system fuses data from onboard sensors including the inertial measurement unit (IMU), barometer, and optical flow camera using an extended Kalman filter (EKF). The efficiency of this approach was validated through simulation experiments involving a UAV navigating in a circular and square motions. Statistical analysis confirmed the proposed system can provide state estimation and smooth trajectory control for UAVs during GPS signal outages. © 2024 ISIF. | P14: IMU; Navigation; Optical Flow; UAVs | Q14: 2-s2.0-85207692634
A15: Zahid M.U.; Nisar M.D.; Fazil A.; Ryu J.; Shah M.H. | B15: Zahid, Muhammad Usama (57965916300); Nisar, Muhammad Danish (17435054000); Fazil, Adnan (56121926300); Ryu, Jihyoung (36519735000); Shah, Maqsood Hussain (57206854889) | C15: 57965916300; 17435054000; 56121926300; 36519735000; 57206854889 | D15: Composite Ensemble Learning Framework for Passive Drone Radio Frequency Fingerprinting in Sixth-Generation Networks | E15: 2024 | F15: Sensors | G15: 24 | H15: 17 | I15: 5618 | M15: 10.3390/s24175618 | N15: https://www.scopus.com/inward/record.uri?eid=2-s2.0-85203871690&doi=10.3390%2fs24175618&partnerID=40&md5=2433f2c778c82a41d55170afbe1d6537 | O15: The rapid evolution of drone technology has introduced unprecedented challenges in security, particularly concerning the threat of unconventional drone and swarm attacks. In order to deal with threats, drones need to be classified by intercepting their Radio Frequency (RF) signals. With the arrival of Sixth Generation (6G) networks, it is required to develop sophisticated methods to properly categorize drone signals in order to achieve optimal resource sharing, high-security levels, and mobility management. However, deep ensemble learning has not been investigated properly in the case of 6G. It is anticipated that it will incorporate drone-based BTS and cellular networks that, in one way or another, may be subjected to jamming, intentional interferences, or other dangers from unauthorized UAVs. Thus, this study is conducted based on Radio Frequency Fingerprinting (RFF) of drones identified to detect unauthorized ones so that proper actions can be taken to protect the network’s security and integrity. This paper proposes a novel method—a Composite Ensemble Learning (CEL)-based neural network—for drone signal classification. The proposed method integrates wavelet-based denoising and combines automatic and manual feature extraction techniques to foster feature diversity, robustness, and performance enhancement. Through extensive experiments conducted on open-source benchmark datasets of drones, our approach demonstrates superior classification accuracies compared to recent benchmark deep learning techniques across various Signal-to-Noise Ratios (SNRs). This novel approach holds promise for enhancing communication efficiency, security, and safety in 6G networks amidst the proliferation of drone-based applications. © 2024 by the authors. | P15: deep ensemble learning; deep learning; drone fingerprint; ensemble learning; RF fingerprinting; specific emitter identification | Q15: 2-s2.0-85203871690
A16: Liaquat S.; Faizan M.; Chattha J.N.; Butt F.A.; Mahyuddin N.M.; Naqvi I.H. | B16: Liaquat, Salman (58725072100); Faizan, Muhammad (57195627743); Chattha, Jawwad Nasar (26029321500); Butt, Faran Awais (55825797000); Mahyuddin, Nor Muzlifah (24448238900); Naqvi, Ijaz Haider (23009130600) | C16: 58725072100; 57195627743; 26029321500; 55825797000; 24448238900; 23009130600 | D16: A framework for preventing unauthorized drone intrusions through radar detection and GPS spoofing | E16: 2024 | F16: Ain Shams Engineering Journal | G16: 15 | H16: 5 | I16: 102707 | M16: 10.1016/j.asej.2024.102707 | N16: https://www.scopus.com/inward/record.uri?eid=2-s2.0-85186886308&doi=10.1016%2fj.asej.2024.102707&partnerID=40&md5=1558b9002875c0b5d44d3ec9f070785d | O16: The increasing use of Global Positioning System (GPS)-based autonomous drones in various civilian and military applications has raised concerns about malicious or unintentionally harmful activities that can be carried through them. It is necessary to detect these intruding drones within protected areas and prevent their unauthorized access by denying them entry. We propose a framework that combines the detection of intruding drones using an L-band radar and then counters by transmitting fake GPS coordinates toward the drones, effectively redirecting them. This article explains the setup required to add to an existing monostatic radar that provides two-dimensional information, i.e., range and azimuth information, to enable the proposed setup to get the elevation angle of the drone. We propose a linear array design using digital receive-only beamforming techniques in the elevation domain to compute the elevation angle in addition to the range, velocity, and azimuth information being provided by the monostatic radar to get complete information about the intruding drone. The simulation of drone detection is followed by an examination of the impact of transmitting fabricated GPS coordinates to the drone. Experimental verification has been conducted to validate both the digital beamforming algorithm and the spoofing technique. This approach blocks the reception of actual GPS signals in the drone and replaces the drone's GPS coordinates with alternative, desired coordinates. The proposed framework can be used to prevent unauthorized drone intrusions in the protected area. © 2024 The Author(s) | P16: Digital beamforming; Drones; Global Positioning System (GPS); Pulse-Doppler radar; Software-Defined Radios (SDRs); Spoofing; Unmanned Aerial Vehicles (UAVs) | Q16: 2-s2.0-85186886308
A17: Thangam S.; Gupta P.K.; Kartthikeyan N.; Mukil L.D.; Niranjan D.K. | B17: Thangam, S. (35173605500); Gupta, Pradeep Kumar (59421081700); Kartthikeyan, N. (59420934200); Mukil, L.D. (59420022400); Niranjan, D.K. (57219282984) | C17: 35173605500; 59421081700; 59420934200; 59420022400; 57219282984 | D17: Low-Cost Network Jammer for Wi-Fi Network in Civilian Areas | E17: 2024 | F17: Proceedings of the 5th International Conference on Smart Electronics and Communication, ICOSEC 2024 | J17: 666 | K17: 672 | L17: 6 | M17: 10.1109/ICOSEC61587.2024.10722738 | N17: https://www.scopus.com/inward/record.uri?eid=2-s2.0-85209943378&doi=10.1109%2fICOSEC61587.2024.10722738&partnerID=40&md5=8e29ddee59542601e00e8cafbb626128 | O17: This application presents a novel approach to address the challenge of intercepting unmanned aerial vehicles (UAVs) operating within the 2.4 GHz frequency band. Jamming device operating at 2.4 GHz, with an Arduino Nano microcontroller and nRF24L01 module included. The device is designed to accurately search available wireless networks in a specific frequency range, focused on intercepting connections between drones in this spectrum Real-time system identifies networks and selects the channels, thus disconnecting targeted frequency devices Security measures in the presence of counter-drone activities are required This technology is an important tool for growth. Using Arduino Nano and nRF24L01 modules, the jamming device offers a flexible and scalable solution designed for network security professionals. The 2.4 GHz jammer provides precise interference, allowing targeted disruption of drones operating in a specific frequency band. In addition, the paper provides a detailed introduction to well-known drones operating in the 2.4 GHz frequency range, such as the DJI Phantom series and the Parrot Bebop series, and understanding these drones is crucial for planning effective countermeasures. The paper includes implementation data and results of experimental tests, providing insights into the efficiency and feasibility of a 2.4 GHz jammer designed to combat interference in UAV networks in a specific frequency band to be used. © 2024 IEEE. | P17: 2.4 GHz; Network disturbance; Security; Wi-Fi disturbance | Q17: 2-s2.0-85209943378
A18: Petro P.; Bauer P. | B18: Petro, Peter (59309498100); Bauer, Peter (57220722317) | C18: 59309498100; 57220722317 | D18: Mono camera-based GPS spoofing detection for aerial vehicles | E18: 2024 | F18: IFAC-PapersOnLine | G18: 58 | H18: 4 | J18: 126 | K18: 131 | L18: 5 | M18: 10.1016/j.ifacol.2024.07.205 | N18: https://www.scopus.com/inward/record.uri?eid=2-s2.0-85202902745&doi=10.1016%2fj.ifacol.2024.07.205&partnerID=40&md5=88153416f1521eefad3021579044342d | O18: This paper presents mono camera-based GPS spoofing detection for aerial vehicles utilizing only image information besides the initial orientation of the vehicle. Orientation information is propagated and motion direction is estimated solely from the mono camera images through the estimation of the essential matrix. Histograms of Oriented Displacements and their correlation are considered to detect spoofing considering GPS and image-based data. Straight and turning simulated fight trajectories of a fixed wing research drone with different turbulence levels are compared to evaluate the method. The results are promising with timely detection of every spoofing scenario and without false alarm. The exploration of real fight data is the topic of future development. © 2024 The Authors. This is an open access article under the CC BY-NC-ND license. | P18: GPS spoofing detection; mono camera relative motion; UAV | Q18: 2-s2.0-85202902745
A19: Alquwayzani A.A.; Albuali A.A. | B19: Alquwayzani, Alanoud A. (58297749000); Albuali, Abdullah A. (57196185950) | C19: 58297749000; 57196185950 | D19: A Systematic Literature Review of Zero Trust Architecture for Military UAV Security Systems | E19: 2024 | F19: IEEE Access | G19: 12 | J19: 176033 | K19: 176056 | L19: 23 | M19: 10.1109/ACCESS.2024.3503587 | N19: https://www.scopus.com/inward/record.uri?eid=2-s2.0-85210298511&doi=10.1109%2fACCESS.2024.3503587&partnerID=40&md5=adb708bc137d1c71da1901c726cafeb7 | O19: Over the last couple of years, the application of autonomous systems such as drones has been widely accepted, and these applications are used in the defense, safety, logistics, delivery, and consumer sectors. Unmanned Aerial Vehicles (UAVs) play a major role in contemporary battles by collecting intelligence, surveillance, reconnaissance, and aiding tactical procedures. Although the intricate interlinking of these systems and the high rate of cyber risk pose security challenges, there are ways to overcome them. Traditional security approaches based on border patrols and protective measures are unreliable against advanced and persistent threats. As a result, the Zero Trust (ZT) approach, which operates under the notion that no faith can be taken for granted in the network, is certainly the most appropriate way to deal with this issue. The main purpose of zero trust in UAV security is to reduce the vulnerability of the system to cyber threats. The core of zero trust is based on observing all activities and risks. This approach will help military UAV operators allow only genuine users to access UAV systems, thereby reducing the possibility of illegal access, hacking, and data breaches. This project aims to analyze the applicability of a zero-trust architecture model and machine learning to enhance the security of military drones. This study conducted a systematic review aimed at identifying different aspects of cybersecurity strategies for protecting UAV systems. Furthermore, a zero-trust architecture is presented in this study as an effective prospective solution to the security issues. © 2013 IEEE. | P19: cybersecurity; drone; Internet of Battlefield Things (IoBT); military UAVs; Security; suspicious behavior; UAV; UAV security; zero trust architecture (ZTA) | Q19: 2-s2.0-85210298511
A20: Sabuwala N.A.; Daruwala R.D. | B20: Sabuwala, Noshin A. (58122117800); Daruwala, Rohin D. (35795271200) | C20: 58122117800; 35795271200 | D20: An approach to enhance the security of unmanned aerial vehicles (UAVs) | E20: 2024 | F20: Journal of Supercomputing | G20: 80 | H20: 7 | J20: 9609 | K20: 9639 | L20: 30 | M20: 10.1007/s11227-023-05811-1 | N20: https://www.scopus.com/inward/record.uri?eid=2-s2.0-85179310352&doi=10.1007%2fs11227-023-05811-1&partnerID=40&md5=f1a96cb99d846bae7139d6fb6a47ff5d | O20: There is a significant surge in unmanned aerial vehicles’ (UAVs) popularity with an ongoing increase in demand due to their multi-functional uses. The capacity of the UAVs to respond to society and industry needs account for their pervasiveness. UAVs can be strategically deployed to enhance network efficiency and support critical missions, including vital tasks like infrastructure monitoring operations. To be effective, a UAV must interact securely with its network’s entities, such as ground control stations, other UAVs, air traffic control systems, and navigation satellite systems. UAVs are exposed to a dangerous and costly world of cyber dangers as a result of cyber technology and connections. The UAV and the Ground Control Station (GCS) exchange information using communication lines, which are vulnerable to cyber-attacks. As a result, detective, defensive, and preventative countermeasures are critical. The Micro Air Vehicle Link (MAVLink) protocol is a widely used lightweight communication protocol for enabling communication between UAVs and GCSs. It outlines communication exchanges between a GCS and a UAV. It carries information about the UAV’s condition as well as commands for control from the GCS. Although widely used, the MAVLink protocol lacks sufficient security measures and is susceptible to various types of attacks, which can pose significant risks to public safety. UAV data should be encrypted because they are very sensitive. To give a high level of security, complex operation encryption techniques are developed. These mathematical operations bring forth issues with efficiency and power usage, though. One of these methods, the ChaCha cipher, recently gained popularity after Google used it in several applications. In the current study, a new stream cipher method with low-duty cycles is proposed for protecting data in UAVs and is compared with existing security algorithms on the basis of various factors. The research findings show that by including the suggested method in MAVLink, it is possible to maintain both message secrecy and battery life for a resource-constrained UAV. This can be done while using comparable amounts of memory and CPU and without affecting MAVLink’s performance. © The Author(s), under exclusive licence to Springer Science+Business Media, LLC, part of Springer Nature 2023. | P20: Communication security; Internet of things (IoT); MAVLink; Stream cipher; Unmanned aerial vehicles (UAVs) | Q20: 2-s2.0-85179310352
A21: Anghuwo J.S.; Imanuel P.; Nangolo S.S. | B21: Anghuwo, John Shivute (59129871600); Imanuel, Peter (59129684000); Nangolo, Sam Shimakeleni (59128922100) | C21: 59129871600; 59129684000; 59128922100 | D21: Anti-unmanned aerial vehicle detection system for airports: aviation and national security perspective | E21: 2024 | F21: Journal of Transportation Security | G21: 17 | H21: 1 | I21: 12 | M21: 10.1007/s12198-024-00280-w | N21: https://www.scopus.com/inward/record.uri?eid=2-s2.0-85193254114&doi=10.1007%2fs12198-024-00280-w&partnerID=40&md5=760c51441934acfdeefd202f86a6ca51 | O21: Unmanned Aerial Vehicles gained significant popularity in the last decade as demonstrated by their wide usage in various fields. From around the year 2001, the usage of unmanned aerial vehicles’ technology was mainly confined to law enforcement agencies such as the military, police, and customs. In the contemporary, terrorists have also been observed to be using unmanned aerial vehicles to attack aviation facilities. The current paper examines the levels of vulnerability of the Namibian airports to possible intrusion and attack from unmanned aerial vehicles, a situation that could pose a serious threat to aviation and national security. Adopting a qualitative research approach, the study made use of a questionnaire and semi-structured interview guide to collect primary data from the participants. Microsoft Excel was used to analyse the data. The study establishes that Namibian airports are prone to attacks from unmanned aerial vehicles as there are no anti-unmanned aerial vehicle detection systems installed at all airports in the country. Thus, there is clear evidence that the Namibia Civil Aviation Authority and the Namibian Airport Company’s regulations and policies on aviation safety and security did not prioritise the installation of anti-unmanned aerial vehicle detection systems at all airports in Namibia. The paper suggests that, in order to enhance aviation safety and security, a joint civil/military Information Technology Unit, responsible for spoofing, detection, and the monitoring of illicit unmanned aerial vehicle operations should be set up and operations activated at all airports and other public infrastructures in Namibia. © The Author(s) 2024. | P21: Airports’ vulnerability; Anti-unmanned aerial vehicle detection system; Aviation safety and security; National security; UAV attack; UAVs | Q21: 2-s2.0-85193254114
A22: Alzahrani M.Y. | B22: Alzahrani, Mohammed Y. (56125509600) | C22: 56125509600 | D22: Enhancing Drone Security Through Multi-Sensor Anomaly Detection and Machine Learning | E22: 2024 | F22: SN Computer Science | G22: 5 | H22: 5 | I22: 651 | M22: 10.1007/s42979-024-02983-2 | N22: https://www.scopus.com/inward/record.uri?eid=2-s2.0-85195944082&doi=10.1007%2fs42979-024-02983-2&partnerID=40&md5=6200a876d8badd2677146c02a2082dfb | O22: Unmanned Aerial Vehicles (UAVs), commonly referred to as drones, have determined numerous applications across industries, ranging from aerial surveillance to package shipping. As drones are used in vital operations, ensuring cyberattacks and anomalies protect them from attackers is now a big challenge. This research study presents a complete approach to enhancing drone safety by integrating multi-sensor anomaly detection and superior machine learning techniques. The proposed methodology capitalizes on the rich sensor suite embedded in present-day drones, encompassing GPS receivers, accelerometers, gyroscopes, cameras, communication modules, and more. Leveraging an array of sensors in drones, our technique detects abnormal drone behavior indicative of unauthorized access, GPS spoofing, communication jamming, and malicious activities. By extracting features from sensor records, we develop a robust anomaly detection framework using the “uav attack dataset” able to identify deviations from normal flight patterns, communication signals, and environmental interactions. Central to our methodology is the utilization of machine learning algorithms. These algorithms are skilled on labeled datasets containing numerous flight eventualities, each normal and hostile, together with the ones discovered inside the “uav attack dataset”. The obtained results are eventually evaluated using rigorous performance metrics to quantify their effectiveness in distinguishing genuine anomalies from benign variations. The findings of our study underscore the capacity of multi-sensor anomaly detection for drones. By harnessing the power of machine learning and sensor fusion, we exhibit the ability to hit upon attacks at an early level, mitigating capability harm and permitting rapid responses. This study contributes now not only to the field of drone safety but also to the broader panorama of self-sustaining systems protection, highlighting the importance of adaptive and proactive protection mechanisms. Results show that an accuracy of 99% with AUC of 100$ was achieved when all the sensors were used. © The Author(s), under exclusive licence to Springer Nature Singapore Pte Ltd. 2024. | P22: Anomaly Detection; Drone Security; Machine Learning for Drones; Multi-Sensor Anomaly Detection; Sensor Fusion | Q22: 2-s2.0-85195944082
A23: Vithalani M.; Vaghela R.S.; Gohil J.A.; Gaylah K.D. | B23: Vithalani, Manav (59463957500); Vaghela, Ravirajsinh S. (57195488524); Gohil, Jaypalsinh A. (57215415981); Gaylah, Kwitee D. (58114309900) | C23: 59463957500; 57195488524; 57215415981; 58114309900 | D23: Drone Neutralization: A Comprehensive Framework for Detecting and Disrupting Malicious Drone Operations | E23: 2024 | F23: Lecture Notes in Networks and Systems | G23: 1095 LNNS | J23: 451 | K23: 460 | L23: 9 | M23: 10.1007/978-981-97-6318-4_35 | N23: https://www.scopus.com/inward/record.uri?eid=2-s2.0-85211320869&doi=10.1007%2f978-981-97-6318-4_35&partnerID=40&md5=cddd2b819c88abf76f339b00b5dfc136 | O23: With the increasing prevalence of drones and their susceptibility to wireless attacks, the need for effective countermeasures is crucial to safeguard civilian and military areas. This research paper presents a comprehensive methodology for neutralizing drones engaged in malicious activities, utilizing wireless network scanning, packet injection techniques, and cyber-attack approaches. The proposed framework encompasses four major steps: detection, reconnaissance, deauthentication, and gaining access or deactivation. Experimental testing demonstrates the successful implementation of the methodology, achieving results in detecting, disconnecting, and neutralizing drones. The framework offers distinct advantages over existing countermeasures, providing a proactive and real-time approach to countering the drone threat. This research contributes to the field of drone security by providing practical insights and tactics for mitigating potential risks posed by malicious drone operations, thus enhancing the overall protection of civilian and military sectors. © The Author(s), under exclusive license to Springer Nature Singapore Pte Ltd. 2024. | P23: Drone detection systems; Drone neutralization; Drone-to-ground communication; Drones security; Unmanned Aerial Vehicle (UAV); Wireless attacks | Q23: 2-s2.0-85211320869
A24: Adel A.; Jan T. | B24: Adel, Amr (57219892693); Jan, Tony (7004322283) | C24: 57219892693; 7004322283 | D24: Watch the Skies: A Study on Drone Attack Vectors, Forensic Approaches, and Persisting Security Challenges | E24: 2024 | F24: Future Internet | G24: 16 | H24: 7 | I24: 250 | M24: 10.3390/fi16070250 | N24: https://www.scopus.com/inward/record.uri?eid=2-s2.0-85199668263&doi=10.3390%2ffi16070250&partnerID=40&md5=da172daa57e7020632607b69caf26688 | O24: In the rapidly evolving landscape of drone technology, securing unmanned aerial vehicles (UAVs) presents critical challenges and demands unique solutions. This paper offers a thorough examination of the security requirements, threat models, and solutions pertinent to UAVs, emphasizing the importance of cybersecurity and drone forensics. This research addresses the unique requirements of UAV security, outlines various threat models, and explores diverse solutions to ensure data integrity. Drone forensics, a field dedicated to the investigation of security incidents involving UAVs, has been extensively examined and demonstrates its relevance in identifying attack origins or establishing accident causes. This paper further surveys artifacts, tools, and benchmark datasets that are critical in the domain of drone forensics, providing a comprehensive view of current capabilities. Acknowledging the ongoing challenges in UAV security, particularly given the pace of technological advancement and complex operational environments, this study underscores the need for increased collaboration, updated security protocols, and comprehensive regulatory frameworks. Ultimately, this research contributes to a deeper understanding of UAV cybersecurity and aids in fostering future research into the secure and reliable operation of drones. © 2024 by the authors. | P24: drone cybersecurity; drone forensics; forensic methodologies; security challenges; threat models; unmanned aerial vehicles (UAVs) | Q24: 2-s2.0-85199668263
A25: Selvan C.; Ragunathan A.; Ashwinkumar U.M. | B25: Selvan, C. (57191914884); Ragunathan, Aravindhan (58964794700); Ashwinkumar, U.M. (55201370200) | C25: 57191914884; 58964794700; 55201370200 | D25: Mitigating phishing threats in Unmanned Aircraft Systems (UAS) through multi-stage defense strategies | E25: 2024 | F25: Analyzing and Mitigating Security Risks in Cloud Computing | J25: 125 | K25: 162 | L25: 37 | M25: 10.4018/979-8-3693-3249-8.ch007 | N25: https://www.scopus.com/inward/record.uri?eid=2-s2.0-85189125432&doi=10.4018%2f979-8-3693-3249-8.ch007&partnerID=40&md5=8bd4b87dd3cfd9ac226aa627184b5be2 | O25: Phishing attacks, while more commonly associated with targeting individuals or organizations through traditional communication channels like email or social media, pose potential threats to unmanned aircraft systems (UAS) or drones. Although not as prevalent in this domain, there exist scenarios where phishing tactics could compromise UAS operations and data. Attackers might impersonate legitimate UAS entities, crafting emails that appear credible and relevant to UAS operations. A multi-stage approach incorporating natural language processing and machine learning is introduced to combat such threats. This approach employs techniques like conditional random field (CRF) and latent Dirichlet allocation (LDA) to detect phishing attacks and discern manipulated content. A novel web crawler utilizing web ontology language (OWL) is devised, leveraging semantic relationships to filter out fake sites from search results. The experimental results demonstrate the effectiveness of these methods in detecting and preventing phishing attacks across different platforms. © 2024, IGI Global. All rights reserved. | Q25: 2-s2.0-85189125432
A26: Ajakwe S.O.; Kim D.-S. | B26: Ajakwe, Simeon Okechukwu (57414321100); Kim, Dong-Seong (55586876300) | C26: 57414321100; 55586876300 | D26: Facets of security and safety problems and paradigms for smart aerial mobility and intelligent logistics | E26: 2024 | F26: IET Intelligent Transport Systems | G26: 18 | H26: S1 | J26: 2827 | K26: 2855 | L26: 28 | M26: 10.1049/itr2.12579 | N26: https://www.scopus.com/inward/record.uri?eid=2-s2.0-85209788941&doi=10.1049%2fitr2.12579&partnerID=40&md5=5b57fb249577ba50eccff2093249ae2d | O26: The use of unmanned aerial vehicles (UAVs) for smart and speedy logistics is still relatively nascent compared to traditional delivery methods. However, it is witnessing sporadic and steady growth due to booming demands, technological advancement, and regulatory support. The intelligence and integrity of UAV systems depend largely on the underlying cognitive and cybersecurity models, which serve as both eyes and brains to perceive and respond to the myriad of scenarios around them. Smart mobility and intelligent logistic ecosystems (SMiLE) are complex and advanced technological networks which are exposed to several issues. The incorporation of UAVs for priority logistics, thereby extending the coverage and capacity of SMiLE, further heightens these vulnerabilities and questions its security, safety, and sustainability. This review scrutinizes the significant security disruptions, smartness dynamics, and sundry developments for the sustainable deployment of UAVs as an aerial logistics-based vehicle. Using the PRISMA-SPIDER methodology, 157 articles were selected for quantitative analysis and 20 review articles for qualitative evaluation. Security and safety issues in UAVs cut across all the layers of logistics operations: components, communication, network architecture, navigation, supply chain etc. Expanding the capacity of SMiLE using UAV demands an intentional and incremental convergence-based integration of an agile explainable artificial framework for reliable and safety-conscious smart mobility, a scalable and tamperproof blockchain for multi-factor authentication, and a zero trust cybersecurity paradigm for inclusive enterprise-based authorization. © 2024 The Author(s). IET Intelligent Transport Systems published by John Wiley & Sons Ltd on behalf of The Institution of Engineering and Technology. | P26: artificial intelligence; blockchain; cyber attacks; drones; logistics; security; smart mobility; zero trust architecture | Q26: 2-s2.0-85209788941
A27: Wang J.; Wang R. | B27: Wang, Jubo (59326695600); Wang, Ruixin (59446141400) | C27: 59326695600; 59446141400 | D27: Multi-UAV Area Coverage Track Planning Based on the Voronoi Graph and Attention Mechanism | E27: 2024 | F27: Applied Sciences (Switzerland) | G27: 14 | H27: 17 | I27: 7844 | M27: 10.3390/app14177844 | N27: https://www.scopus.com/inward/record.uri?eid=2-s2.0-85203857976&doi=10.3390%2fapp14177844&partnerID=40&md5=73186b20a0030bf43217d2d4b2b4a675 | O27: Drone area coverage primarily involves using unmanned aerial vehicles (UAVs) for extensive monitoring, surveying, communication, and other tasks over specific regions. The significance and value of this technology are multifaceted. Firstly, UAVs can rapidly and efficiently reach remote or inaccessible areas to perform tasks such as terrain mapping, disaster monitoring, or search and rescue, significantly enhancing response speed and execution efficiency. Secondly, drone area coverage in agricultural monitoring, forestry conservation, and urban planning offers high-precision data support, aiding scientists and decision-makers in making more accurate judgments and decisions. Additionally, drones can serve as temporary communication base stations in areas with poor communication, ensuring the transfer of crucial information. Drone area coverage technology is vital in improving work efficiency, reducing costs, and strengthening decision support. This paper aims to solve the optimization problem of multi-UAV area coverage flight path planning to enhance system efficiency and task execution capability. For multi-center optimization problems, a region decomposition method based on the Voronoi graph is designed, transforming the multi-UAV area coverage issue into the single-UAV area coverage problem, greatly simplifying the complexity and computational process. For the single-UAV area coverage problem and its corresponding area, this paper contrives a convolutional neural network with the channel and spatial attention mechanism (CSAM) to enhance feature fusion capability, enabling the model to focus on core features for solving single-UAV path selection and ultimately generating the optimal path. Simulation results demonstrate that the proposed method achieves excellent performance. © 2024 by the authors. | P27: area coverage; channel and spatial attention mechanism; flight path planning; multi-UAV; Voronoi graph | Q27: 2-s2.0-85203857976
A28: Psilias D.; Milidonis A.; Lentaris G.; Voyiatzis I. | B28: Psilias, Dimitrios (57222337130); Milidonis, Athanasios (9734400200); Lentaris, George (23987718500); Voyiatzis, Ioannis (18438856600) | C28: 57222337130; 9734400200; 23987718500; 18438856600 | D28: Secure Video and Telemetry FPGA Architecture For UAVs | E28: 2024 | F28: Proceedings - 2024 9th South-East Europe Design Automation, Computer Engineering, Computer Networks and Social Media Conference, SEEDA-CECNSM 2024 | J28: 69 | K28: 74 | L28: 5 | M28: 10.1109/SEEDA-CECNSM63478.2024.00021 | N28: https://www.scopus.com/inward/record.uri?eid=2-s2.0-85210857383&doi=10.1109%2fSEEDA-CECNSM63478.2024.00021&partnerID=40&md5=46d785e5cff9afabcd907d18f3143694 | O28: Unmanned Aerial Vehicles (UAVs) are used in a wide range of applications. However, since they are vulnerable to cyberattacks security protocols for their data are used. Common existing approaches for data encryption/decryption are based on commercial software platforms which execute their tasks with latency and consume a lot of energy. Moreover, they focus mostly on encrypting/decrypting telemetry data. This paper proposes a Field Programming Gate Array (FPGA)-based architecture for encrypting/decrypting all data exchanged between UAVs and their Ground Station (GS). This architecture uses the Advanced Encryption Standard (AES), known for its robustness, to enhance the confidentiality, integrity, and security. Experimental results show that the proposed architecture performs faster than implementations on well-known software platforms while it consumes less power. © 2024 IEEE. | P28: AES; decryption; drone; encryption; FPGA; UAV | Q28: 2-s2.0-85210857383
A29: Usamentiaga R. | B29: Usamentiaga, Ruben (6507926393) | C29: 6507926393 | D29: Semiautonomous Pipeline Inspection Using Infrared Thermography and Unmanned Aerial Vehicles | E29: 2024 | F29: IEEE Transactions on Industrial Informatics | G29: 20 | H29: 2 | J29: 2540 | K29: 2550 | L29: 10 | M29: 10.1109/TII.2023.3295409 | N29: https://www.scopus.com/inward/record.uri?eid=2-s2.0-85165902794&doi=10.1109%2fTII.2023.3295409&partnerID=40&md5=385eb2b3dbf6371f7de29f8e754bf0ec | O29: Pipeline inspection is crucial to ensure the safe and efficient operation of pipelines, as well as to prevent potential hazards and disruptions in the transportation of materials. To address this challenge, this work proposes an innovative semiautonomous inspection method that uses unmanned aerial vehicles and infrared thermography to efficiently inspect pipelines. The approach combines the benefits of automated flight and high-speed data acquisition with advanced data processing techniques, enabling the detection of hidden defects and abnormal temperature patterns in pipelines. The proposed procedure presents a comprehensive operational approach that covers the entire inspection process, including flight configuration, data acquisition, and processing. The proposed method for data processing is automated, utilizing vision-based detection and tracking techniques, and leveraging the power of deep learning algorithms to ensure robust analysis and inspection. A novel active learning procedure is also proposed, further improving the efficiency and effectiveness of the pipeline inspection process. Extensive tests demonstrate the effectiveness of the proposed procedure in industrial applications. The proposed thermographic system enables the detection and localization of insulation defects and product leaks in pipes, which are critical for maintaining pipeline integrity. © 2005-2012 IEEE. | P29: Active learning; detection and tracking; infrared thermography; pipeline inspection; unmanned aerial vehicles (UAVs) | Q29: 2-s2.0-85165902794
A30: Faouz S.A.E.; Souri A.; Inanc N. | B30: Faouz, Sami Abou El (59485953500); Souri, Alireza (56901126500); Inanc, Nihat (7004144256) | C30: 59485953500; 56901126500; 7004144256 | D30: LSTM-based Deep Learning Model for Cyber-attack Detection Systems in the Internet of Drones | E30: 2024 | F30: 2024 15th International Conference on Computing Communication and Networking Technologies, ICCCNT 2024 | M30: 10.1109/ICCCNT61001.2024.10726101 | N30: https://www.scopus.com/inward/record.uri?eid=2-s2.0-85213037317&doi=10.1109%2fICCCNT61001.2024.10726101&partnerID=40&md5=4276a4851028bbacf8b9e0e0a38b29e5 | O30: The Internet of drones (IoD) has emeregd as a hot topic in the technology industry and is deemed important and useful to several applications and fields where we see dozens of drones deployed to achieve a particular mission. The huge benefits sometimes can be a mask for some of the crucial issues that can affect this field of the UAVs crucially and we are talking about security and privacy. The internet of drones comes to connect between drones making them smart but leaving an open door for intruders to exploit. This paper will uphold a model that utilizes the wonders of deep learning to improve it greatly. In this proposed model, a LSTM algorithm is applied to further enhance the capability and reliability of the deep learning model. Using evaluation factors such as accuracy, precision, and etc. we can see that our model outperforms other ML algorithms and classifiers while having a low training time which showcases the efficiency of LSTM-based deep learning model. © 2024 IEEE. | P30: Deep Learning; IDS; Internet Of Drones; LSTM; UAV | Q30: 2-s2.0-85213037317
A31: Tedeschi P.; Al Nuaimi F.A.; Awad A.I.; Natalizio E. | B31: Tedeschi, Pietro (57205428562); Al Nuaimi, Fatima Ali (57219701927); Awad, Ali Ismail (42961080300); Natalizio, Enrico (8897972900) | C31: 57205428562; 57219701927; 42961080300; 8897972900 | D31: Privacy-Aware Remote Identification for Unmanned Aerial Vehicles: Current Solutions, Potential Threats, and Future Directions | E31: 2024 | F31: IEEE Transactions on Industrial Informatics | G31: 20 | H31: 2 | J31: 1069 | K31: 1080 | L31: 11 | M31: 10.1109/TII.2023.3280325 | N31: https://www.scopus.com/inward/record.uri?eid=2-s2.0-85161566703&doi=10.1109%2fTII.2023.3280325&partnerID=40&md5=043b80e3beae5c9cd14d89251928abb8 | O31: The Federal Aviation Administration (FAA) recently introduced a new standard, namely, remote identification, to improve accountability for unmanned aerial vehicles (UAVs) operations. This rule requires UAV operators to broadcast messages revealing sensitive data, such as identity and location on the wireless channel. However, this leads to security and privacy concerns among UAV operators. Unauthorized parties may easily discover the location and identity of a UAV flying in a specific area and launch attacks on it such as using wireless jamming or tracking its activity. This review investigates and systematizes the main weaknesses affecting the Remote ID capability required of modern UAVs, and the approaches through which attackers can exploit these weaknesses to disrupt safety and accountability. Moreover, this article analyzes current solutions that mitigate privacy issues associated with Remote ID. Finally, we identify multiple challenges that require to be addressed by both industry and academia, and we propose future research directions to improve the security and privacy of UAVs. © 2005-2012 IEEE. | P31: Anonymity; privacy; remote ID; security; unmanned aerial vehicles (UAVs) | Q31: 2-s2.0-85161566703
A32: Kloepper L.N.; Taylor G.K.; Domski P.; Vanderelst D.; Eveland K.; Stevenson R.L. | B32: Kloepper, L.N. (36462426000); Taylor, G.K. (7404202352); Domski, P. (59155508700); Vanderelst, D. (23480664700); Eveland, K. (59155884400); Stevenson, R.L. (7402603265) | C32: 36462426000; 7404202352; 59155508700; 23480664700; 59155884400; 7402603265 | D32: HawkEar: A bird-borne visual and acoustic platform for eavesdropping the behaviour of mobile animals | E32: 2024 | F32: Methods in Ecology and Evolution | G32: 15 | H32: 7 | J32: 1150 | K32: 1157 | L32: 7 | M32: 10.1111/2041-210X.14329 | N32: https://www.scopus.com/inward/record.uri?eid=2-s2.0-85195141100&doi=10.1111%2f2041-210X.14329&partnerID=40&md5=9a9ecc7d271d07dec65c5a39c68df0d8 | O32: Unoccupied aerial vehicles (UAVs; drones) offer mobile platforms for ecological investigation, but can be impractical in some environments and the resulting noise can disturb wildlife. We developed a mobile alternative using a bird-borne platform to record the behaviour of other animals in the field. This unit consists of a lightweight audio and video sensor that is carried by a trained Harris's hawk Parabuteo unicinctus. We tested the hypothesis that our bird-borne platform is a viable option for collecting behavioural data from mobile animals. We recorded acoustic and video data as the hawk flew through a dense group of Brazilian free-tailed bats Tadarida brasiliensis emerging from a cave, with a test case of investigating how echolocation calls change depending on spatial position in the bat group. The HawkEar platform is an alternative for collecting behavioural data when a mobile platform that is less noisy and restrictive than traditional UAVs is needed. The design and software are open source and can be modified to accommodate additional sensor needs. © 2024 The Author(s). Methods in Ecology and Evolution published by John Wiley & Sons Ltd on behalf of British Ecological Society. | P32: animal-borne tag; bats; collective behaviour; falconry; hawk; silent monitoring system; UAV | Q32: 2-s2.0-85195141100
A33: Mon Y.-J. | B33: Mon, Yi-Jen (6602110291) | C33: 6602110291 | D33: Correction: Simulation and Implementation of Signal Processing for LFM Radar Using DSK 6713 (Electronics, (2023), 12, 17, (3682), 10.3390/electronics12173682) | E33: 2024 | F33: Electronics (Switzerland) | G33: 13 | H33: 3 | I33: 468 | M33: 10.3390/electronics13030468 | N33: https://www.scopus.com/inward/record.uri?eid=2-s2.0-85184468487&doi=10.3390%2felectronics13030468&partnerID=40&md5=dbe44f74f65097d523b52fa94a7eeed1 | O33: In the original publication [1], references [4,5] need to be corrected in terms of the authors and publishers, and references [6,7,9–24,31] need to be updated to provide correct published references. The citations in the main text do not need to be updated due to the changes in these references. The correct references are listed below: 4. Andersson, U. Time-Domain Methods for the Maxwell Equations. Ph.D. Thesis, KTH Royal Institute of Technology, Stockhalm, Sweden, February 2001. 5. Tait, P. Introduction to Radar Target Recognition; IET Digital Library: Edison, NJ, USA, 2005. 6. Patole, S.M.; Torlak, M.; Wang, D.; Ali, M. Automotive radars: A review of signal processing techniques. IEEE Signal Process Mag. 2017, 34, 22–35. https://doi.org/10.1109/MSP.2016.2628914. 7. Hanif, A.; Muaz, M.; Hasan, A.; Adeel, M. Micro-Doppler Based Target Recognition with Radars: A Review. IEEE Sens. J. 2022, 22, 2948–2961. https://doi.org/10.1109/JSEN.2022.3141213. 9. Liu, Q.; Li, Z.; Yuan, S.; Zhu, Y.; Li, X. Review on Vehicle Detection Technology for Unmanned Ground Vehicles. Sensors 2021, 21, 1354. https://doi.org/10.3390/s21041354. 10. Shariff, K.K.M.; Hoare, E.; Daniel, L.; Antoniou, M.; Cherniakov, M. Comparison of Adaptive Spectral Estimation for Vehicle Speed Measurement with Radar Sensors. Sensors 2017, 17, 751. https://doi.org/10.3390/s17040751. 11. Ahmed, S.; Qiu, B.; Ahmad, F.; Kong, C.-W.; Xin, H. A State-of-the-Art Analysis of Obstacle Avoidance Methods from the Perspective of an Agricultural Sprayer UAV’s Operation Scenario. Agronomy 2021, 11, 1069. https://doi.org/10.3390/agronomy11061069. 12. Başpınar, Ö.O.; Omuz, B.; Öncü, A. Detection of the Altitude and On-the-Ground Objects Using 77-GHz FMCW Radar Onboard Small Drones. Drones 2023, 7, 86. https://doi.org/10.3390/drones7020086 13. Guerra, A.; Dardari, D.; Djurić, P.M. Dynamic Radar Network of UAVs: A Joint Navigation and Tracking Approach. IEEE Access 2020, 8, 116454–116469. https://doi.org/10.1109/ACCESS.2020.3001393. 14. Wessendorp, N.; Dinaux, R.; Dupeyroux, J.; de Croon, G.C.H.E. Obstacle Avoidance onboard MAVs using a FMCW Radar. In Proceedings of the 2021 IEEE/RSJ International Conference on Intelligent Robots and Systems (IROS), Prague, Czech Republic, 27 September 2021–1 October 2021. 15. Tierney, B.B.; Rodenbeck, C.T. 3D-Sensing MIMO Radar for UAV Formation Flight and Obstacle Avoidance. In Proceedings of the 2019 IEEE Radio and Wireless Symposium (RWS), Orlando, FL, USA, 20–23 January 2019. https://doi.org/10.1109/RWS.2019.8714287. 16. Shi, C.; He, J.; Han, X.; Zhang, X. Research on anti-jamming technology of missile-borne radar seeker in complex electromagnetic environment. In Proceedings of the 2022 IEEE International Conference on Electrical Engineering, Big Data and Algorithms (EEBDA), Changchun, China, 25–27 February 2022. 17. Yuan, M.; Zhang, L.; Wang, Y.; Han, C. Polarimetric Range Extended Target Detection via Adaptive Range Weighted Feature Extraction. Remote Sens. 2023, 15, 2929. https://doi.org/10.3390/rs15112929. 18. Lakshminaray anan, A.P.; Kumawat, H.C.; Raj, A.B. Moving Target Detection in Foliage Environment using FMCW Radar. In Proceedings of the 2020 5th International Conference on Communication and Electronics Systems (ICCES), Coimbatore, India, 10–12 June 2020. 19. Li, G.; Ge, Y.; Wang, Y.; Chen, Q.; Wang, G. Detection of Human Breathing in Non-Line-of-Sight Region by Using mmWave FMCW Radar. IEEE Trans. Instrum. Meas. 2022, 71, 1–11. 20. Jin, K.; Li, G.; Lai, T.; Jin, T.; Zhao, T. A Novel Long-Time Coherent Integration Algorithm for Doppler-Ambiguous Radar Maneuvering Target Detection. IEEE Sens. J. 2020, 20, 9394–9407. https://doi.org/10.1109/JSEN.2020.2988583. 21. Addabbo, P.; Bernardi, M.L.; Biondi, F.; Cimitile, M.; Clemente, C.; Orlando, D. Temporal Convolutional Neural Networks for Radar Micro-Doppler Based Gait Recognition. Sensors 2021, 21, 381. https://doi.org/10.3390/s21020381 22. Liu, J.; Zhang, K.; Sun, Z.; Wu, Q.; He, W.; Wang, H. Concealed Object Detection and Recognition System Based on Millimeter Wave FMCW Radar. Appl. Sci. 2021, 11, 8926. https://doi.org/10.3390/app11198926 23. Rouveure, R.; Faure, P.; Monod, M.-O. PELICAN: Panoramic millimeter-wave radar for perception in mobile robotics applications, Part 1: Principles of FMCW radar and of 2D image construction. Rob. Autom. Syst. 2016, 81, 1–16. https://doi.org/10.1016/j.robot.2016.04.001. 24. Vivet, D.; Checchin, P.; Chapuis, R. Localization and Mapping Using Only a Rotating FMCW Radar Sensor. Sensors 2013, 13, 4527–4552. https://doi.org/10.3390/s130404527. 31. Tavanti, E.; Rizik, A.; Fedeli, A.; Caviglia, D.D.; Randazzo, A. A Short-Range FMCW Radar-Based Approach for Multi-Target Human-Vehicle Detection. IEEE Trans. Geosci. Remote Sens. 2022, 60, 1–16. https://doi.org/10.1109/TGRS.2021.3138687. The author states that the scientific conclusions are unaffected. This correction was approved by the Academic Editor. The original publication has also been updated. © 2024 by the author. | Q33: 2-s2.0-85184468487
A34: Elia R.; Rak M.; Pascarella D. | B34: Elia, Raffaele (59144040600); Rak, Massimiliano (8966231800); Pascarella, Domenico (25823435600) | C34: 59144040600; 8966231800; 25823435600 | D34: A First Step Towards an Automated Methodology for the Security Risk Assessment of U-Space Solutions | E34: 2024 | F34: Proceedings - 2024 IEEE 21st International Conference on Mobile Ad-Hoc and Smart Systems, MASS 2024 | J34: 676 | K34: 681 | L34: 5 | M34: 10.1109/MASS62177.2024.00108 | N34: https://www.scopus.com/inward/record.uri?eid=2-s2.0-85210256685&doi=10.1109%2fMASS62177.2024.00108&partnerID=40&md5=be8b1ab89d6d5acc0015f788d4e31be8 | O34: U-space is an European initiative for developing a framework to support drone operations, as well as a clear and effective interface to manned aviation, by means of a fully automated drone management system. With the U-space revolution, drones are going to pose an ever-evolving threat landscape with complex multi-domain security risks. Thus, U-space security is a primary challenge, requiring proper security-by-design approaches. In addition, research should address automated security risk assessment for facing the U-space complexity and for increasing the cost-efficiency of engineering secure U-space systems. This work proposes a preliminary definition of a methodology relying on formalisms, techniques and tools for the automated security risk assessment of U-space solutions. As a first step, a model-based methodology is investigated for a semi-automatic impact assessment of attacks on U-space. Some preliminary results are presented for a case study about drone-based pharmaceutical delivery in U-space environment. © 2024 IEEE. | P34: Cybersecurity; Drones; SecRAM; Security Risk Assessment; U-space; UAS; UAV; Unmanned Traffic Management | Q34: 2-s2.0-85210256685
A35: Maqbool A.; Slimane J.B.; Khediri N.; Ammar M.B.; Kachoukh A.; Alshammari A. | B35: Maqbool, Albia (58885542400); Slimane, Jihane Ben (36844049300); Khediri, Nouha (57447487200); Ammar, Mohamed Ben (36800833900); Kachoukh, Amani (57744142900); Alshammari, Ahmad (59000865700) | C35: 58885542400; 36844049300; 57447487200; 36800833900; 57744142900; 59000865700 | D35: PROACTIVE CYBER DEFENSE AND FORENSIC INVESTIGATION TECHNIQUES FOR DRONE OPERATION: A HOLISTIC APPROACH | E35: 2024 | F35: Journal of Theoretical and Applied Information Technology | G35: 102 | H35: 18 | J35: 6697 | K35: 6709 | L35: 12 | N35: https://www.scopus.com/inward/record.uri?eid=2-s2.0-85206446209&partnerID=40&md5=bf0ec7a31e9d9fbae40831a362d732a3 | O35: The integration of drones into various sectors, such as logistics, surveillance, agriculture, and emergency response, has revolutionized operational capabilities. However, this advancement has also exposed drones to significant cybersecurity threats, necessitating robust forensic investigation techniques. This paper presents a comprehensive approach to enhancing cyber defense mechanisms and forensic investigation methodologies specifically tailored for drone operations. Leveraging deep learning and machine learning techniques, our proposed framework aims to detect, mitigate, and investigate cyber threats targeting drones in real-time. The framework was developed and validated using a combination of publicly available datasets, including the DARPA UAV attack scenarios dataset and UNSW-NB15 network intrusion data, as well as data from controlled drone operation simulations that replicated real-world scenarios, such as surveillance and delivery missions under cyber-attack conditions. This comprehensive approach allows for a holistic evaluation of the framework’s effectiveness across various cyber-attack types. The publicly available datasets include UAV attack scenarios and network intrusion data, which cover a wide range of cyber threats. Additionally, we collected data from simulations of different drone operations, including surveillance and delivery missions, under various cyber-attack conditions. The proposed framework demonstrates significant improvements in real-time threat detection for drones, utilizing deep learning and machine learning techniques. The framework was tested using both publicly available datasets and simulations of drone operations under various attack scenarios, achieving high accuracy (95.3%), precision (94.8%), recall (93.7%), and F1-score (94.2%) for CNN-based threat detection. These results highlight the robustness of our approach in enhancing the security and reliability of drone operations. The study contributes to the field of drone cybersecurity by offering a scalable and real-time defense mechanism, supported by a forensic investigation framework. Comparisons with existing techniques highlight significant improvements achieved by our approach. Furthermore, we present case studies that illustrate the practical application of our framework in real-world scenarios, showcasing its capability to handle both cyber-attack and forensic investigation situations effectively. Finally, we address the challenges and limitations encountered during the research, providing insights into potential future work. This paper contributes significantly to the field of drone cybersecurity and forensic investigation, offering a holistic approach that enhances the safety and reliability of drone operations. © Little Lion Scientific. | P35: Anomaly Detection; Case Studies; Cyber Defense Framework; Deep Learning; Digital Forensics; Drone Cybersecurity; Forensic Investigation; Machine Learning; Network Intrusion Data; Performance Metrics; Threat Detection; UAV Attack Scenarios | Q35: 2-s2.0-85206446209
A36: Mohammed A.B.; Chaari Fourati L.; Fakhrudeen A.M. | B36: Mohammed, Ahmed Burhan (57686887900); Chaari Fourati, Lamia (58235960400); Fakhrudeen, Ahmed M. (57193843395) | C36: 57686887900; 58235960400; 57193843395 | D36: Isolation Forest Algorithm Against UAV's GPS Spoofing Attack | E36: 2024 | F36: Proceedings - IEEE Congress on Cybermatics: 2024 IEEE International Conferences on Internet of Things, iThings 2024, IEEE Green Computing and Communications, GreenCom 2024, IEEE Cyber, Physical and Social Computing, CPSCom 2024, IEEE Smart Data, SmartData 2024 | J36: 459 | K36: 463 | L36: 4 | M36: 10.1109/iThings-GreenCom-CPSCom-SmartData-Cybermatics62450.2024.00090 | N36: https://www.scopus.com/inward/record.uri?eid=2-s2.0-85210552942&doi=10.1109%2fiThings-GreenCom-CPSCom-SmartData-Cybermatics62450.2024.00090&partnerID=40&md5=62370c6f688e4bd751b2f26b425ca266 | O36: Nowadays, Unmanned Aerial Vehicle (UAV) platforms are a valuable source of data for inspection, surveillance, mapping, and 3D modeling issues. Embedded electronic and communication systems within UAVs are based on the integration of the Internet of Things (IoT) into UAV systems (commonly called the Internet of Drone Things (IoDT)). Nevertheless, the vulnerability of this interconnected environment to malicious activities, such as GPS spoofing, threatens the dependability and security of UAV operations. To countermeasure this challenging issue, this article uses an effective anomaly detection method, the Isolation Forest algorithm, for mitigating GPS spoofing threats. A well-curated dataset specifically targeting the detection of GPS deception in UAVs has been utilized. Extensive experiments were conducted to compare our proposal with its counterparts (Random Forest and Naive Bayes). The experimental outcomes demonstrate the Isolation Forest algorithm's efficiency in anomaly detection, attaining a noteworthy accuracy rate of (95.85%). However, Random Forest and Naive Bayes achieved (93.63%) and (92.38%), respectively. Other performance evaluation metrics show that the Isolation Forest works better than others, which supports its potential as a reliable way for anomaly detection when GPS spoofing happens in UAVs. The insight obtained from this research can provide valuable input for creating proactive security protocols to guarantee the secure implementation and functioning of UAVs. © 2024 IEEE. | P36: Anomaly Detection; GPS spoofing; Internet of Things; Isolation Forest algorithm; UAV | Q36: 2-s2.0-85210552942
A37: Khan M.A.; Javaid S.; Mohsan S.A.H.; Tanveer M.; Ullah I. | B37: Khan, Muhammad Asghar (59397585700); Javaid, Shumaila (57212490992); Mohsan, Syed Agha Hassnain (57218375194); Tanveer, Muhammad (57214601656); Ullah, Insaf (59435184600) | C37: 59397585700; 57212490992; 57218375194; 57214601656; 59435184600 | D37: Future-Proofing Security for UAVs With Post-Quantum Cryptography: A Review | E37: 2024 | F37: IEEE Open Journal of the Communications Society | G37: 5 | J37: 6849 | K37: 6871 | L37: 22 | M37: 10.1109/OJCOMS.2024.3486649 | N37: https://www.scopus.com/inward/record.uri?eid=2-s2.0-85208113366&doi=10.1109%2fOJCOMS.2024.3486649&partnerID=40&md5=b7bf1318a54c38e682a17fd1dea8c7df | O37: Unmanned Aerial Vehicles (UAVs), commonly known as drones, are increasingly being employed across a broad spectrum of applications, ranging from military operations to commercial purposes. However, as UAVs become more integrated into everyday life, security and privacy concerns are similarly escalating due to vulnerabilities arising from operating on open wireless channels and having limited onboard computational resources. Moreover, with the emergence of quantum computers, conventional cryptographic methods that ensure the security and privacy of UAV communications are at severe risk. These risks encompass the possibility of unauthorized access, breaches of data, and cyber-physical attacks that jeopardize the integrity, confidentiality, and availability of UAV operations. Quantum computers are expected to break the conventional cryptography methods, such as symmetric and asymmetric schemes, with the support of Grover's and Shor's algorithms, respectively. Consequently, traditional cryptographic algorithms must give way to quantum-resistant algorithms, referred to as Post-Quantum Cryptography (PQC) algorithms. Although researchers actively develop, test, and standardize new PQC algorithms, the threat persists despite the progress made through these consistent efforts. This review article first examines the security and privacy landscape, including threats and requirements of UAVs. This article also discusses PQC and various PQC families and the status of the NIST's implementation and standardization process. Lastly, we explore challenges and future directions in implementing PQC for UAVs. © 2020 IEEE. | P37: Post-quantum cryptography; privacy; quantum attacks; security; UAVs | Q37: 2-s2.0-85208113366
A38: Nyangaresi V.O.; Al-Joboury I.M.; Al-sharhanee K.A.; Najim A.H.; Abbas A.H.; Hariz H.M. | B38: Nyangaresi, Vincent Omollo (57220777100); Al-Joboury, Istabraq M. (57197755180); Al-sharhanee, Kareem Ali (58577672100); Najim, Ali Hamzah (57216411619); Abbas, Ali Hashim (57387015700); Hariz, Hussein Muhi (57348783800) | C38: 57220777100; 57197755180; 58577672100; 57216411619; 57387015700; 57348783800 | D38: A biometric and physically unclonable function–Based authentication protocol for payload exchanges in internet of drones | E38: 2024 | F38: e-Prime - Advances in Electrical Engineering, Electronics and Energy | G38: 7 | I38: 100471 | M38: 10.1016/j.prime.2024.100471 | N38: https://www.scopus.com/inward/record.uri?eid=2-s2.0-85186492164&doi=10.1016%2fj.prime.2024.100471&partnerID=40&md5=12738f48a9413d4489cd426571f3ae72 | O38: Internet of Drones (IoD) has been deployed in numerous military and civilian domains to offer services such as target surveillance, traffic monitoring, disaster handling and environmental monitoring. However, message exchanges among the drones and ground station servers are via insecure wireless channels. In addition, drones may be deployed in hostile and unattended locations. This renders the IoD susceptible to numerous privacy and security threats such as drone capture and cloning. Therefore, many security solutions have been developed based on techniques such as blockchain and public key infrastructure. However, majority of these schemes are still susceptible to many attacks while some of them are inefficient for the resource-limited IoD devices. In this paper, a Physically Unclonable Function (PUF) challenge-response and biometric based robust authentication protocol is presented. Its formal security is carried out using the Real or Random (RoR) model, which demonstrates the robustness of the negotiated session key. In addition, its semantic analysis shows that it can withstand typical IoD attacks such as impersonation, replay, de-synchronization and spoofing. In terms of performance, it is shown to incur lower computation, energy and communication costs. © 2024 The Author(s) | P38: Attacks; Authentication; Drones; Privacy; Security; UAVs | Q38: 2-s2.0-85186492164
A39: Miao S.; Pan Q.; Zheng D.; Mohi-ud-din G. | B39: Miao, Shangting (57716814700); Pan, Quan (7202997700); Zheng, Dongxiao (58861178900); Mohi-ud-din, Ghulam (57904661300) | C39: 57716814700; 7202997700; 58861178900; 57904661300 | D39: Unmanned aerial vehicle intrusion detection: Deep-meta-heuristic system | E39: 2024 | F39: Vehicular Communications | G39: 46 | I39: 100726 | M39: 10.1016/j.vehcom.2024.100726 | N39: https://www.scopus.com/inward/record.uri?eid=2-s2.0-85184024780&doi=10.1016%2fj.vehcom.2024.100726&partnerID=40&md5=2a7d7bfbd1ed4352b5d9938aa6af57e5 | O39: The UAV (Unmanned Aerial Vehicles) is an automatic aircraft, widely used several applications like emergency management, wildlife conservation, forestry, aerial photography, etc. The communication among the UAV is susceptible to security threats with several diverse attacks. The data sharing among the UAV and other vehicles is vulnerable to jamming and suspicious activities that disturbs the communication. To tackle the issue, IDS (Intrusion Detection System) is the significant system that monitors and identifies the suspicious activities in the communication network. To attain this, several conventional researchers attempted to accomplish better intrusion detection. However, classical models are limited by accuracy, noise and computation. To overcome the limitation, proposed method employs particular set of procedures for the intrusion detection in UAV with Intrusion UAV dataset. The dataset comprise of features like drone speed, height, width, velocity etc. Initially, in the respective approach, GG (Greedy based Genetic) algorithm for feature selection, which maintains the exact balance between the greediness and diversified population. Greedy approach enhances Genetic algorithm in combinatorial optimisation problems. Further, the study proposes Modified Deep CNN-BiLSTM (Deep Convolutional Neural Network and Bi-Long Short Term Memory) with attention mechanism for classification of intrusion in UAV. The deep CNN is utilized for the ability of handling larger datasets and accuracy. Conversely, it is limited by computation and speed. To tackle the problem, Bi-LSTM is used for the capability of enhancing the computation and speed. Moreover, attention mechanism is used for handle the complexity and to permit the presented system to focus on the significant and relevant data. Correspondingly, proposed approach performance is calculated using performance metrics such as accuracy, specificity, sensitivity, R2 (R-Squared), execution time, RMSE and precision. Furthermore, comparative analysis of the proposed method and classical model exposes the efficacy of the respective system. © 2024 Elsevier Inc. | P39: Bi-directional long short term memory; Deep convolutional neural network; Greedy based genetic algorithm; Intrusion detection system; Unmanned aerial vehicle | Q39: 2-s2.0-85184024780
A40: Procksch N.; Guimarães M.; Trindade M.R.; Ott P.H.; Perez M.S.; Veronez M.R.; de Oliveira L.R. | B40: Procksch, Natália (57219932317); Guimarães, Murilo (40461390800); Trindade, Marcela Regina (59219552400); Ott, Paulo Henrique (23390585200); Perez, Martin Sucunza (57681863400); Veronez, Maurício Roberto (26023922300); de Oliveira, Larissa Rosa (55191597100) | C40: 57219932317; 40461390800; 59219552400; 23390585200; 57681863400; 26023922300; 55191597100 | D40: How close can we get to seeing the private lives of fur seals and sea lions? Experimental UAV flights on the Southern Brazilian coast | E40: 2024 | F40: Journal of Experimental Marine Biology and Ecology | G40: 579 | I40: 152042 | M40: 10.1016/j.jembe.2024.152042 | N40: https://www.scopus.com/inward/record.uri?eid=2-s2.0-85198567597&doi=10.1016%2fj.jembe.2024.152042&partnerID=40&md5=c89112e9fbe62080f4ad123d3633b30b | O40: Recent advances in unmanned aerial vehicle (UAV) technology have made them a popular and accessible tool for wildlife research. Despite their popularity, there are some concerns about their potential negative impacts due to the possibility of causing disturbance to the species being monitored. We assessed the potential behavioral disturbance of low altitude UAVs on South American fur seals (Arctocephalus australis) and sea lions (Otaria flavescens) on a haulout site in southern Brazil (Wildlife Refuge of Ilha dos Lobos (WRIL)) between October 2022 and August 2023. Behavioral responses of each individual toward the UAV were classified (no response, vigilant or movement) and individuals were also classified according to their species. The probability of individuals expressing each one of the three behaviors at each altitude was assessed by Binomial and Multinomial Mixed Models. We flew a small UAV (DJI Air 2S) vertically above 731 South American sea lions, including 131 adult males, 590 subadult males and 10 juveniles; and 121 South American fur seals, including one subadult, one juvenile and 119 yearlings. For sea lions, vigilant and movement responses represented only 7.70% and 0.36% of behaviors observed during vertical approaches. South American fur seals appeared less perturbed by UAV presence, as only 1.56% of observed behaviors were classified as vigilant, and no movement responses were observed during vertical approaches. Similar results were found during horizontal flights over these species. The most frequent behavior observed in both species was no response, with a probability higher than 0.89 during vertical and horizontal approaches with drones, even at lower altitudes. Based on these results, we recommend that due to their benefits and minimal impact on the studied species, UAV monitoring studies of South American pinnipeds be conducted at a minimum altitude of 30 m at non-breeding sites, especially at haulout sites. © 2023 | P40: Arctocephalus australis; Behavior; Drone disturbance; Otaria flavescens | Q40: 2-s2.0-85198567597
A41: Branco B.; Silva J.S.; Correia M. | B41: Branco, Bruno (59487292200); Silva, José Silvestre (57197594594); Correia, Miguel (22333381700) | C41: 59487292200; 57197594594; 22333381700 | D41: D3S: A Drone Security Scoring System | E41: 2024 | F41: Information (Switzerland) | G41: 15 | H41: 12 | I41: 811 | M41: 10.3390/info15120811 | N41: https://www.scopus.com/inward/record.uri?eid=2-s2.0-85213081002&doi=10.3390%2finfo15120811&partnerID=40&md5=6a6f3f7aa60fd21b01e7b0c8c0df5ee2 | O41: This paper explores the problem of the security of unmanned aerial vehicles (UAV) by introducing the drone security scoring system (D3S). D3S is a security assessment method that analyzes the security of a UAV model by analyzing its components. Penetration tests were carried out to support D3S and identify potential vulnerabilities in UAVs. Specific cyber-attacks, such as deauthentication, flooding, and replay, were executed in an effort to take full control of the UAVs. Eight different UAV models were assessed using D3S, revealing notable variations in performance, both in control communications and video transmission. Security scores ranging from 0.9 to 4.5 out of 5 were obtained, showing significantly divergent security levels. © 2024 by the authors. | P41: command and control; communication; cyber-attacks; cybersecurity; drone security scoring system; unmanned aerial vehicle; vulnerability | Q41: 2-s2.0-85213081002
A42: Xu Q.; Yi J.; Wang X.; Niu M.-B.; Miah M.S.; Wang L. | B42: Xu, Qian (56834870900); Yi, Jia (59387434300); Wang, Xianyu (59387640000); Niu, Ming-Bo (57881091800); Miah, Md. Sipon (55843135700); Wang, Ling (59088364400) | C42: 56834870900; 59387434300; 59387640000; 57881091800; 55843135700; 59088364400 | D42: Secure Unmanned Aerial Vehicle Communication in Dual-Function Radar Communication System by Exploiting Constructive Interference | E42: 2024 | F42: Drones | G42: 8 | H42: 10 | I42: 581 | M42: 10.3390/drones8100581 | N42: https://www.scopus.com/inward/record.uri?eid=2-s2.0-85207660625&doi=10.3390%2fdrones8100581&partnerID=40&md5=75b2f3fdd1ed49fb046f1aa9e2146d9c | O42: In contrast from traditional unmanned aerial vehicle communication via unlicensed spectrum, connecting unmanned aerial vehicles with cellular networks can extend their communication coverage and improve the quality of their service. In addition, the emerging dual-functional radar communication paradigm in cellular systems can better meet the requirements of location-sensitive tasks such as reconnaissance and cargo delivery. Based on the above considerations, in this paper, we study the simultaneous communication and target sensing issue in cellular-connected unmanned aerial vehicle systems. Specifically, we consider a two-cell coordinated system with two base stations, cellular unmanned aerial vehicles, and potential aerial targets. In such systems, the communication security issue of cellular unmanned aerial vehicles regarding eavesdropping on their target is inevitable since the main beam of the transmit waveform needs to point to the direction of the target for achieving a sufficient detection performance. Aiming at protecting the privacy of cellular transmission as well as performing target sensing, we exploit the physical layer security technique with the aid of constructive interference-based precoding. A transmit power minimization problem is formulated with constraints on secure and reliable cellular transmission and a sufficient radar signal-to-interference-plus-noise ratio. By specially designing the transmit beamforming vectors at the base stations, the received signals at the cellular users are located in the decision regions of the transmitted symbols while the targets can only receive wrong symbols. We also compare the performance of the proposed scheme with that of the traditional one without constructive interference. The simulation results show that the proposed constructive interference-based strategy can meet the requirements of simultaneous target sensing and secure communication, and also save transmit power compared with the traditional scheme. © 2024 by the authors. | P42: beamforming; constructive interference; drone communications; dual-function radar communication; physical layer security | Q42: 2-s2.0-85207660625
A43: Pu C.; Warner C.; Choo K.-K.R.; Lim S.; Ahmed I. | B43: Pu, Cong (56430573100); Warner, Clare (58725451900); Choo, Kim-Kwang Raymond (57208540261); Lim, Sunho (8437951300); Ahmed, Imtiaz (57196854804) | C43: 56430573100; 58725451900; 57208540261; 8437951300; 57196854804 | D43: liteGAP: Lightweight Group Authentication Protocol for Internet of Drones Systems | E43: 2024 | F43: IEEE Transactions on Vehicular Technology | G43: 73 | H43: 4 | J43: 5849 | K43: 5860 | L43: 11 | M43: 10.1109/TVT.2023.3335839 | N43: https://www.scopus.com/inward/record.uri?eid=2-s2.0-85178014504&doi=10.1109%2fTVT.2023.3335839&partnerID=40&md5=28e3212d23c88803fe1d82c07794be4c | O43: Over the past few years, the synergic usage of unmanned aerial vehicles (later drones) and Internet of Things (IoT) has successfully transformed into the Internet of Drones (IoD) paradigm, where the data of interest is gathered and delivered to the Zone Service Provider (ZSP) by drones for substantial additional analysis. Considering the sensitivity of collected information and the impact of information disclosure, information privacy and security issues should be resolved properly so that the maximum potential of IoD can be realized in the increasingly complex cyber threat environment. Ideally, an authentication and key agreement protocol can be adopted to establish secure communications between drones and the ZSP in an insecure environment. Nevertheless, a large group of drones authenticating with the ZSP simultaneously will lead to a severe authentication signaling congestion, which inevitably degrades the quality of service (QoS) of IoD systems. To properly address the above-mentioned issues, a lightweight group authentication protocol, called liteGAP, is proposed in this paper. liteGAP can achieve the authenticated key establishment between a group of drones and the ZSP concurrently in the IoD environment using lightweight operations such as hash function, bitwise XOR, and physical unclonable function (PUF). We verify liteGAP using AVISPA (a tool for the automatic verification of security protocols) and conduct formal and informal security analysis, proving that liteGAP meets all pre-defined security requirements and withstand various potential cyber attacks. Moreover, we develop an experimental framework and conduct extensive experiments on liteGAP and two benchmark schemes (e.g., GASE and rampIoD). Experimental findings show that liteGAP outperforms its counterparts in terms of computational cost as well as communication overhead. © 1967-2012 IEEE. | P43: group authentication; Information privacy and security; Internet of Drones; signaling congestion | Q43: 2-s2.0-85178014504
A44: Tang C.; Ding J.; Qi H.; Zhang L. | B44: Tang, Chengkai (36643012300); Ding, Jiawei (58068845800); Qi, Huaiyuan (58481366500); Zhang, Lingling (57193262550) | C44: 36643012300; 58068845800; 58481366500; 57193262550 | D44: Smart forwarding deceptive jamming distribution optimal algorithm | E44: 2024 | F44: IET Radar, Sonar and Navigation | G44: 18 | H44: 6 | J44: 953 | K44: 964 | L44: 11 | M44: 10.1049/rsn2.12540 | N44: https://www.scopus.com/inward/record.uri?eid=2-s2.0-85185666095&doi=10.1049%2frsn2.12540&partnerID=40&md5=19ae43cf21db165ab7f31783364f7efa | O44: With the frequent occurrence of drone black flying in large stadiums and airports, the requirement of precise electromagnetic interference to achieve unmanned aerial vehicle (UAV) displacement and forced landing in these protected area became urgent. Since traditional suppression jamming will affect normal communication, and forwarding deceptive jamming has coverage hole, a smart forwarding deceptive jamming distribution optimal algorithm (SFDJDO) is proposed. It gives a mapping error scale factor and the optimal distribution of multistation forwarding equivalent mapping to solve the problem of distortion on the mapping scale caused by different distribution methods and reduces the influence of the mapping errors and the differences between the virtual and real point neighborhoods of the jamming source. A comparison of the proposed SFDJDO method to the existing jamming source distribution optimisation method is conducted in the aspect of area mapping and trajectory mapping. The findings reveal that when the GNSS receiver clock bias is within the capture range, SFDJDO demonstrates significant enhancements in mapping precision and jamming success rates. © 2024 The Authors. IET Radar, Sonar & Navigation published by John Wiley & Sons Ltd on behalf of The Institution of Engineering and Technology. | P44: feedforward neural nets; GNSS jamming; normal distribution; optimisation | Q44: 2-s2.0-85185666095
A45: Hong Y.-W.; Yoo D.-Y. | B45: Hong, Young-Woo (59216961400); Yoo, Dong-Young (59217825800) | C45: 59216961400; 59217825800 | D45: Multiple Intrusion Detection Using Shapley Additive Explanations and a Heterogeneous Ensemble Model in an Unmanned Aerial Vehicle’s Controller Area Network | E45: 2024 | F45: Applied Sciences (Switzerland) | G45: 14 | H45: 13 | I45: 5487 | M45: 10.3390/app14135487 | N45: https://www.scopus.com/inward/record.uri?eid=2-s2.0-85198432615&doi=10.3390%2fapp14135487&partnerID=40&md5=ec42d326f1fd551cd08d28d0231cf558 | O45: Recently, methods to detect DoS and spoofing attacks on In-Vehicle Networks via the CAN protocol have been studied using deep learning models, such as CNN, RNN, and LSTM. These studies have produced significant results in the field of In-Vehicle Network attack detection using deep learning models. However, these studies have typically addressed studies on single-model intrusion detection verification in drone networks. This study developed an ensemble model that can detect multiple types of intrusion simultaneously. In preprocessing, the patterns within the payload using the measure of Feature Importance are distinguished from the attack and normal data. As a result, this improved the accuracy of the ensemble model. Through the experiment, both the accuracy score and the F1-score were verified for practical utility through 97% detection performance measurement. © 2024 by the authors. | P45: controller area network (CAN); deep learning (DL); ensemble model; intrusion detection; machine learning (ML); Shapley additive explanations (SHAP); unmanned aerial vehicles (UAVs) | Q45: 2-s2.0-85198432615
A46: Jin W.-C.; Kim K.; Choi J.-W. | B46: Jin, Woo-Cheol (57216269989); Kim, Kyungtae (56401277600); Choi, Ji-Woong (23392263200) | C46: 57216269989; 56401277600; 23392263200 | D46: Adaptive Beam Control Considering Location Inaccuracy for Anti-UAV Systems | E46: 2024 | F46: IEEE Transactions on Vehicular Technology | G46: 73 | H46: 2 | J46: 2320 | K46: 2331 | L46: 11 | M46: 10.1109/TVT.2023.3320176 | N46: https://www.scopus.com/inward/record.uri?eid=2-s2.0-85173026426&doi=10.1109%2fTVT.2023.3320176&partnerID=40&md5=c2a2fbf457ff2753632cbae2c9d06eab | O46: The threat posed by drones has significantly increased in recent years, necessitating the development of robust anti-UAV systems capable of detecting and preventing malicious UAVs. However, the anti-UAV system requires accurate UAV location detection capabilities to counteract UAVs robustly. For example, when employing jamming technology as a countermeasure, the anti-UAV system can enhance its defence performance by concentrating the jamming signal towards the detected UAV location, a technique known as a directional jamming signal. However, obtaining accurate UAV location information is challenging due to the small size, high velocity, and maneuverability of UAVs, which pose difficulties in detecting and tracking UAVs. Inaccurate UAV location data can significantly impair the defence performance of anti-UAV systems. In the jamming system, it causes the misalignment between the directional jamming signal and the malicious UAV and jamming failure. Therefore, addressing the problem of inaccurate location information is crucial for the anti-UAV system to achieve robust jamming performance. This article investigates the impact of UAV detection errors in an anti-UAV system that employs radar for detection and jamming technology as a countermeasure. We design the UAV detection algorithm to analyze the influence of UAV location detection errors. Furthermore, a beam control scheme is proposed for the jamming system to mitigate the effects of detection errors in the anti-UAV system. The proposed scheme utilizes a wide beam width when location information is inaccurate to avoid beam misalignment. In contrast, a narrow beamwidth is employed when the location information is precise to enhance jamming power efficiency. Simulation results demonstrate that the proposed method ensures stable jamming performance even when faced with inaccurate UAV location information. © 1967-2012 IEEE. | P46: Anti-UAV system; beam misalignment; beamforming; jamming; radar | Q46: 2-s2.0-85173026426
A47: Gutsa T.; Trois C.; de Vries R.; Mani T. | B47: Gutsa, Tadiwanashe (59165610700); Trois, Cristina (14042684600); de Vries, Robin (57618415400); Mani, Thomas (56996987800) | C47: 59165610700; 14042684600; 57618415400; 56996987800 | D47: Wasted shores: Using drones to monitor the spatio-temporal evolution of debris accumulation hotspots on South Africa's Umgeni River | E47: 2024 | F47: Science of the Total Environment | G47: 955 | I47: 176791 | M47: 10.1016/j.scitotenv.2024.176791 | N47: https://www.scopus.com/inward/record.uri?eid=2-s2.0-85206258227&doi=10.1016%2fj.scitotenv.2024.176791&partnerID=40&md5=dbbfa62259ba26939e372ae7865b5991 | O47: Rivers are major contributors of plastic waste to the oceans. Running through the northern part of the 1.3 million-inhabitants City of Durban, South Africa, the Umgeni River is estimated to flush in the order of tens to hundreds of tonnes of plastic waste into the Indian Ocean every year. The riverbanks are lined with plastic and other macro-waste accumulation zones formed due to direct littering and occasional deposition of river debris loads. This study presents the use of Unmanned Aerial Vehicles (UAVs) and hydro-meteorological sensors to (1) identify, quantify and monitor such anthropogenic macro-waste hotspots; and (2) investigate the influence of rainfall, river water level and a major flood event on the spatio-temporal evolution of the hotspots, evidencing the debris' availability to leak into the Indian Ocean. The one-year aerial monitoring (2021−2022) of waste hotspots shows that extreme hydrometeorological events have an immediate but short-term effect on the erosion of debris stocks in riverine systems. We observe that reduction in mean index changes of hotspot surface area after flooding were 2–5 times higher than in non-flood conditions. Despite visual evidence of seasonality in debris erosion between the wet and dry season, only the 'natural' type hotspots showed a significant change. Our findings support reported inconsistencies of macro-debris erosion with hydrological factors. Although the data contributes a baseline for macro-debris erosion in the Umgeni River, future ground truth sampling and finer monitoring scales are important to fully understand debris transfer in river systems. The mapping of waste hotspots and understanding their spatio-temporal transfer dynamics supports policymakers in planning and timing to mitigate environmental pollution. © 2024 The Authors | P47: Coast; Hotspots; Hydro-meteorological; Macro-debris; River; Unmanned Aerial Vehicles; Waste management | Q47: 2-s2.0-85206258227
A48: Adel A.; Alani N.H.S.; Thompson Whiteside S.; Jan T. | B48: Adel, Amr (57219892693); Alani, Noor H. S. (57647203200); Thompson Whiteside, Scott (56747977500); Jan, Tony (7004322283) | C48: 57219892693; 57647203200; 56747977500; 7004322283 | D48: Who is Watching Whom? Military and Civilian Drone: Vision Intelligence Investigation and Recommendations | E48: 2024 | F48: IEEE Access | G48: 12 | J48: 177236 | K48: 177276 | L48: 40 | M48: 10.1109/ACCESS.2024.3505034 | N48: https://www.scopus.com/inward/record.uri?eid=2-s2.0-85210280023&doi=10.1109%2fACCESS.2024.3505034&partnerID=40&md5=ede3f851d73e4cb30be33a38c086be4e | O48: In recent years, there has been a marked increase in the use of drones, with a global surge in the demand for diverse applications. This widespread adoption is largely due to drones' ability to meet various user needs, offering an aerial perspective that can be utilized almost anywhere and at any time. However, the rise in drone usage has also resulted in an increase in malicious use by criminals and cybercriminals. These malicious activities are not only frequent but also potentially harmful, necessitating effective measures for detection, protection, and prevention. This survey aimed to explore the emerging threats posed by drones in cyber-attacks and countermeasures designed to thwart these attacks. It reviews various malicious uses of drones and the possible methods for their detection. Specifically, this study examines vulnerabilities in drone communication links and smart devices, including smartphones and tablets. In addition, it provides a comprehensive review of drone/UAV usage across multiple domains, such as civilian and military activities, highlighting their purposes. A realistic attack scenario is presented, detailing a simulated attack on a drone following a hacking cycle. This review is intended to assist security professionals in understanding the existing vulnerabilities of UAVs in both military and civilian contexts. Furthermore, it aims to inspire the development of new techniques and technologies for enhanced UAV attack detection and protection. As a result, the paper also reviews various civilian and military countermeasures for detecting and preventing drone/UAV threats. This survey differentiates itself by offering a holistic view of drone security, mapping each type of attack onto the corresponding defense mechanisms. It provides a comprehensive review that can serve as a valuable resource for future drone engineers and researchers, helping them to understand the landscape of drone security and develop more effective countermeasures. © 2013 IEEE. | P48: drones attacks; Drones forensics; drones security; drones vulnerabilities; UAV | Q48: 2-s2.0-85210280023
A49: Tassielli G.; Cananà L.; Spalatro M. | B49: Tassielli, Giuseppe (55838747400); Cananà, Lucianna (54411829800); Spalatro, Miriam (59330610000) | C49: 55838747400; 54411829800; 59330610000 | D49: Detection of Methane Leaks via a Drone-Based System for Sustainable Landfills and Oil and Gas Facilities: Effect of Different Variables on the Background-Noise Measurement | E49: 2024 | F49: Sustainability (Switzerland) | G49: 16 | H49: 17 | I49: 7748 | M49: 10.3390/su16177748 | N49: https://www.scopus.com/inward/record.uri?eid=2-s2.0-85204151488&doi=10.3390%2fsu16177748&partnerID=40&md5=80bda5d562e664e00c3825230bee0723 | O49: In recent years, thanks to the great diffusion of drone technology and the development of miniaturized sensors that can be connected to drones, in order to increase the sustainability of landfills and oil and gas facilities, interest in finding methane leaks and quantifying the relative flow has grown significantly. This operation requires the methane background concentration to be subtracted from the calculations. Therefore, in order to proceed with a right estimate of CH4 flows emitted, the possibility of correctly measuring or estimating the background level becomes crucial. The present work intends to illustrate the effects of different variables on the background-noise measurement in a drone-based system that uses a tunable diode laser absorption spectrometer (TDLAS). The methodology used is that of field testing; the data acquisition campaign consisted of the execution of 80 flights during which different flight variables (drone speed, flight altitude) were tested; the flights were repeated in different weather and climate conditions both during the same day and in different periods of the year. Different surfaces, similar to those found in landfill or natural gas sites, were also tested. In some of the field trials, a controlled methane release test was performed in order to verify how much the quantification of the methane flow can vary depending on the background level used. The results of the different field trials highlighted the best conditions under which to measure methane emissions with a TDLAS sensor in order to minimize the number of outliers: flight altitude not exceeding 15 m above ground level; the drone speed appears to have less impact on the results, however, it is optimal between 1 and 2 ms−1; a very sunny day produces much higher methane background levels than a cloudy one. The type of surface also significantly affects the measurement of background noise. Finally, tests conducted with a controlled methane release highlighted that different levels of background have a significant impact on the estimation of the methane flux emitted. © 2024 by the authors. | P49: climate change; drone; fugitive emissions; landfill; methane; TDLAS; UAS | Q49: 2-s2.0-85204151488
A50: Niyonsaba S.; Konate K.; Soidridine M.M. | B50: Niyonsaba, Simon (58686037000); Konate, Karim (37074805000); Soidridine, Moussa Moindze (56073699000) | C50: 58686037000; 37074805000; 56073699000 | D50: Deep Learning Based Intrusion Detection for Cybersecurity in Unmanned Aerial Vehicles Network | E50: 2024 | F50: International Conference on Electrical, Computer, and Energy Technologies, ICECET 2024 | M50: 10.1109/ICECET61485.2024.10698453 | N50: https://www.scopus.com/inward/record.uri?eid=2-s2.0-85207461245&doi=10.1109%2fICECET61485.2024.10698453&partnerID=40&md5=cbd7b220324654710ea92ef08ebfe607 | O50: In this article, we have proposed Deep Learning techniques for cybersecurity in Unmanned Aerial Vehicles (UAVs). UAVs, also known as drones, have become versatile tools used in many applications. However, UA V cybersecurity remains a major concern due to the evolution of cyberattacks. Faced with this issue, it is important to give a contribution on intrusion detection systems (IDS) to be applied in UAVs, given that existing cybersecurity solutions still present limitations. It is in this context that we have proposed Deep Learning-based intrusion detection models such as Convolutional Neural Network (CNN), Long Short-Term Memory (LSTM) and the combination of Convolutional Neural Network (CNN) and Long Short-Term Memory (LSTM) models (CNN+LSTM) and these are evaluated using the CICIDS2017 dataset. Based on their performance, the proposed models are compared with Machine Learning models to decide on the best model for intrusion detection in UAVs. Thus, the results obtained during the experiment indicate that the hybrid CNN-LSTM model obtained a high accuracy of 99.063% compared to the other models. © 2024 IEEE. | P50: CICIDS2017; CNN; cyberattacks; Cybersecurity; Deep Learning; LR; LSTM; Machine Learning; NB; UA V | Q50: 2-s2.0-85207461245
A51: Shariq M.; Conti M.; Singh K.; Dwivedi S.K.; Abdussami M.; Amin R.; Masud M. | B51: Shariq, Mohd (57225464047); Conti, Mauro (15019127200); Singh, Karan (55450561600); Dwivedi, Sanjeev Kumar (56041002800); Abdussami, Mohammad (57821507500); Amin, Ruhul (57210228243); Masud, Mehedi (17338820600) | C51: 57225464047; 15019127200; 55450561600; 56041002800; 57821507500; 57210228243; 17338820600 | D51: Design of Provably Secure and Lightweight Authentication Protocol for Unmanned Aerial Vehicle systems | E51: 2024 | F51: Computer Communications | G51: 228 | I51: 107971 | M51: 10.1016/j.comcom.2024.107971 | N51: https://www.scopus.com/inward/record.uri?eid=2-s2.0-85206458091&doi=10.1016%2fj.comcom.2024.107971&partnerID=40&md5=ff6ec95988db6e1aa069f5add4ad1479 | O51: Drones also called Unmanned Aerial Vehicles (UAVs) have become more prominent in several applications such as package delivery, real-time object detection, tracking, traffic monitoring, security surveillance systems, and many others. As a key member of IoT, the group of Radio Frequency IDentification (RFID) technologies is referred to as Automatic Identification and Data Capturing (AIDC). In particular, RFID technology is becoming a contactless and wireless technique used to automatically identify and track the tagged objects via radio frequency signals. It also has drawn a lot of attention among researchers, scientists, industries, and practitioners due to its broad range of real-world applications in various fields. However, RFID systems face two key concerns related to security and privacy, where an adversary performs eavesdropping, tampering, modification, and even interception of the secret information of the RFID tags, which may cause forgery and privacy problems. In contrast to security and privacy, RFID tags have very limited computational power capability. To deal with these issues, this paper puts forward an RFID-based Lightweight and Provably Secure Authentication Protocol (LPSAP) for Unmanned Aerial Vehicle Systems. The proposed protocol uses secure Physically Unclonable Functions (PUFs), Elliptic-Curve Cryptography (ECC), secure one-way hash, bitwise XOR, and concatenation operations. We use Ouafi and Phan's formal security model for analyzing security and privacy features such as traceability and mutual authentication. The rigorous informal analysis is carried out which ensures that our proposed protocol achieves various security and privacy features as well as resists various known security attacks. The performance analysis demonstrates that our proposed protocol outperforms other existing protocols. In addition, Scyther and Automated Validation of Internet Security Protocols and Applications (AVISPA) tool simulation results demonstrates that there is no security attack possible within bounds. Therefore, our proposed LPSAP protocol achieves an acceptable high level of security with the least computational, communication, and storage costs on passive RFID tags. © 2024 Elsevier B.V. | P51: AIDC; Authentication; IoT; Privacy; RFID; Security | Q51: 2-s2.0-85206458091
A52: Yao L.; Qin H.; Gu B.; Shi G.; Sha H.; Wang M.; Xian D.; Chen F.; Lu Z. | B52: Yao, Lihao (59005567900); Qin, Honglei (8248112800); Gu, Boyun (59005970300); Shi, Guangting (58566012400); Sha, Hai (55235420200); Wang, Mengli (59122871900); Xian, Deyong (57194210260); Chen, Feiqiang (26323196600); Lu, Zukun (57213726777) | C52: 59005567900; 8248112800; 59005970300; 58566012400; 55235420200; 59122871900; 57194210260; 26323196600; 57213726777 | D52: A Study on Anti-Jamming Algorithms in Low-Earth-Orbit Satellite Signal-of-Opportunity Positioning Systems for Unmanned Aerial Vehicles | E52: 2024 | F52: Drones | G52: 8 | H52: 4 | I52: 164 | M52: 10.3390/drones8040164 | N52: https://www.scopus.com/inward/record.uri?eid=2-s2.0-85191558904&doi=10.3390%2fdrones8040164&partnerID=40&md5=75f8ed3f6080875de0f0852ae8ce3d0e | O52: Low-Earth-Orbit (LEO) satellite Signal-of-Opportunity (SOP) positioning technology has gradually matured to meet the accuracy requirements for unmanned aerial vehicle (UAV) positioning in daily scenarios. Advancements in miniaturization technology for positioning terminals have also made this technology’s application to UAV positioning crucial for UAV development. However, in the increasingly complex electromagnetic environment, there remains a significant risk of degradation in positioning performance for UAVs in LEO satellite SOP positioning due to unintentional or malicious jamming. Furthermore, there is a lack of in-depth research from scholars both domestically and internationally on the anti-jamming capabilities of LEO satellite SOP positioning technology. Due to significant differences in the downlink signal characteristics between LEO satellites and Global Navigation Satellite System (GNSS) signals based on Medium Earth Orbit (MEO) or Geostationary Earth Orbit (GEO) satellites, the anti-jamming research results of traditional satellite navigation systems cannot be directly applied. This study addresses the narrow bandwidth and high signal-to-noise ratio (SNR) characteristics of signals from LEO satellite constellations. We propose a Consecutive Iteration based on Signal Cancellation (SCCI) algorithm, which significantly reduces errors during the model fitting process. Additionally, an adaptive variable convergence factor was designed to simultaneously balance convergence speed and steady-state error during the iteration process. Compared to traditional algorithms, simulation and experimental results demonstrated that the proposed algorithm enhances the effectiveness of jamming threshold settings under narrow bandwidth and high-power conditions. In the context of LEO satellite jamming scenarios, it improves the frequency-domain anti-jamming performance significantly and holds high application value for drone positioning. © 2024 by the authors. | P52: low Earth orbit satellite; SCCI algorithms; signal of opportunity; UAV positioning | Q52: 2-s2.0-85191558904
A53: Luo J.; Oracevic A. | B53: Luo, Jiaze (59473906000); Oracevic, Alma (55229307000) | C53: 59473906000; 55229307000 | D53: Adaptive Machine Learning for Efficient Anomaly Detection in Autonomous UAVs Swarm Operations | E53: 2024 | F53: 2024 International Symposium on Networks, Computers and Communications, ISNCC 2024 | M53: 10.1109/ISNCC62547.2024.10758945 | N53: https://www.scopus.com/inward/record.uri?eid=2-s2.0-85212208057&doi=10.1109%2fISNCC62547.2024.10758945&partnerID=40&md5=f16819886bc7d507bff713ed6f5feb6f | O53: Unmanned Aerial Vehicles (UAVs), commonly known as drones are aircraft without a human pilot, crew, or passenger on board. An Unmanned Aerial Vehicle swarm (UAV swarm) usually consists of three or more drones and can execute complex tasks and missions. UAV and UAV Swarm have proliferated these years and have significantly impacted vari-ous fields, including military, agriculture, disaster relief, rescue supplies, and energy management. However, these advantages require enhanced safety measures to prevent group collisions, secure communication within the swarm, and detect abnormal behaviours, including sensor faults and cyber-attacks (e.g., GPS spoofing and command hijacking). This paper proposes an anomaly detection method based on Bi-LSTM with an attention mechanism to identify abnormal behaviours within a UAV swarm. The proposed method uses a supervised approach, training and validating the model with data collected and labelled from self-designed simulated UAV swarm flight experiments. These swarm flight tests include normal flights, flights in windy environments, flights with simulated cyber-attacks and fault injection. These multiple flights enable the model to learn to detect anomalies during formation missions across different conditions. Experimental results demonstrate that the anomaly detection model effectively processes time series data and learns its features from UAV swarm. The evaluation confirms that this method is a sensible solution for detecting anomalies within UAV swarm flights. © 2024 IEEE. | P53: anomaly detection; machine learning; UAV; UAV swarms | Q53: 2-s2.0-85212208057
A54: Singh B. | B54: Singh, Bhupinder (58806881100) | C54: 58806881100 | D54: Unmanned Aircraft Systems (UAS), Surveillance, Risk Management to Cybersecurity and Legal Regulation Landscape: Unraveling the Future Analysis, Challenges, Demand, and Benefits in the High Sky Exploring the Strange New World | E54: 2024 | F54: Unmanned Aircraft Systems | J54: 313 | K54: 354 | L54: 41 | M54: 10.1002/9781394230648.ch8 | N54: https://www.scopus.com/inward/record.uri?eid=2-s2.0-85213774408&doi=10.1002%2f9781394230648.ch8&partnerID=40&md5=449a947ef1f09fd5c454e4d40dbce5c6 | O54: Unmanned aircraft systems (UASs), commonly known as drones, have rapidly transformed from niche technologies to integral components of various industries. Their diverse applications range from surveillance and data collection to logistical support and environmental monitoring. As UASs continue to evolve and proliferate, the complex interplay of factors involving surveillance, risk management, cybersecurity, and legal regulations becomes paramount. This research endeavors to delve into the multifaceted landscape of UAS, exploring their future trajectory, the challenges they pose, the demand they generate, and the benefits they offer, all against the backdrop of an unfamiliar high sky—a strange new world that presents unprecedented opportunities and complexities. The significance of this research lies in its comprehensive examination of the intertwined elements surrounding UAS. Surveillance capabilities of drones are revolutionizing fields such as law enforcement, border security, and wildlife conservation. However, ethical concerns about privacy, data collection, and potential misuse loom large. Effective risk management strategies are imperative to ensure safe UAS operations, safeguarding both human lives and valuable assets. The increasing integration of UASs into critical systems also elevates their vulnerability to cybersecurity threats, necessitating robust protection mechanisms. The legal and regulatory landscape for UASs remains a puzzle to unravel. Balancing innovation with safety and privacy requires adaptable frameworks that evolve with technology. Anticipating the future demand for UAS applications is crucial for industries to stay ahead of the curve. Understanding the benefits—from increased efficiency to reduced environmental impact—underscores their transformative potential. Yet, a thorough assessment of the challenges they introduce, from public acceptance to airspace congestion, cannot be overlooked. In this exploration of the high sky’s strange new world, this research strives to provide insights that guide responsible UAS integration. By addressing these facets holistically, it gains a deeper understanding of the UAS landscape, equipping stakeholders with the knowledge to navigate the complexities and unlock the advantages offered by these remarkable technological advancements. The chapter explores the multifaceted realm of UASs, commonly known as drones, and their implications on surveillance, risk management, cybersecurity, and legal regulations. As these technologies become more integrated into various industries, understanding their future trajectory, challenges, benefits, and legal implications is paramount. In addition, the chapter conducts an in-depth analysis of the evolving landscape, explores potential future developments, identifies challenges, assesses demand, and examines the benefits of UAS applications. By unraveling the complex interactions between technology, security, and regulation, this chapter provides a holistic perspective on the high sky’s strange new world. © 2025 Scrivener Publishing LLC. | P54: Cybersecurity; high sky; legal regulation landscape; surveillance; unmanned aircraft systems (UASs) | Q54: 2-s2.0-85213774408
A55: Zidane Y.; Silva J.S.; Tavares G. | B55: Zidane, Younes (59489981700); Silva, José Silvestre (57197594594); Tavares, Gonçalo (7003985623) | C55: 59489981700; 57197594594; 7003985623 | D55: Jamming and Spoofing Techniques for Drone Neutralization: An Experimental Study | E55: 2024 | F55: Drones | G55: 8 | H55: 12 | I55: 743 | M55: 10.3390/drones8120743 | N55: https://www.scopus.com/inward/record.uri?eid=2-s2.0-85213203017&doi=10.3390%2fdrones8120743&partnerID=40&md5=490c481dd6ee4049b5bad1f0d67550ca | O55: This study explores the use of electronic countermeasures to disrupt communications systems in Unmanned Aerial Vehicles (UAVs), focusing on the protection of airspaces and critical infrastructures such as airports and power stations. The research aims to develop a low-cost, adaptable jamming device using Software Defined Radio (SDR) technology, targeting key UAV communication links, including geolocation, radio control, and video transmission. It applies jamming techniques that successfully disrupt UAV communications. GPS spoofing techniques were also implemented, with both static and dynamic spoofing tested to mislead the drones’ navigation systems. Dynamic spoofing, combined with no-fly zone enforcement, proved to be particularly effective in forcing drones to land or exhibit erratic behavior. The conclusions of this study highlight the effectiveness of these techniques in neutralizing unauthorized UAVs, while also identifying the need for future research in countering drones that operate on alternative frequencies, such as 4G/5G, to enhance the system’s robustness in evolving drone environments. © 2024 by the authors. | P55: drone; jamming; radio frequency; Software Defined Radio (SDR); spoofing; UAV | Q55: 2-s2.0-85213203017
A56: Mehta S.; Aneja A.; Jain V. | B56: Mehta, Shiva (58847208600); Aneja, Aseem (58195947900); Jain, Vishal (57192707657) | C56: 58847208600; 58195947900; 57192707657 | D56: Real-Time Monitoring and Control of Drones Using IoT-Blockchain Integration | E56: 2024 | F56: 2024 International Conference on Electrical, Electronics and Computing Technologies, ICEECT 2024 | M56: 10.1109/ICEECT61758.2024.10739059 | N56: https://www.scopus.com/inward/record.uri?eid=2-s2.0-85211169075&doi=10.1109%2fICEECT61758.2024.10739059&partnerID=40&md5=68792b74c9aca58951f161759bc4ef7d | O56: This work presents an IoT-Blockchain integration solution to enhance the typical Drone systems to acquire optimal organizational performance. Several questions that are associated with modern drone operations are solved by the suggested system, and these questions are the following: data security, efficiency of work, and system scalability. Concerning the experimental results, the boost in the realism of the data transfer rates can also be seen - the mean rate is increased from 500 to 1200 KB/s, thus enabling real-time control. Another effect of Smart Contracts was reducing the time it took to carry out operational activities to which the contracts were applied. For instance, the time taken to route a flight to save time was brought down from 10 minutes to 2 minutes, the time to allocate resources for the flight was brought down from 15 minutes to 3 minutes, and the time to schedule maintenance of the flight was brought down from 20 minutes to 5 minutes. It also presented the framework's performance metrics, such as a 0% data breach incidence rate different from the annual average of 12 in centralized traditional systems. This goes well with Blockchain's ability to house information in a record that can never be altered, providing data security and credibility. However, the system also proved scalability as the number of drones changed from 10 to 100, and the throughput changed from 100 to 920 TPS. Also, the system latency remained below 70 ms during this process, which is critical for responsive trading applications. © 2024 IEEE. | P56: blockchain-based access control scheme; ground station server; internet of drones (IOD); privacy preservation; secure communication; unmanned aerial vehicles (UAVS) | Q56: 2-s2.0-85211169075
A57: Wan Z.; Cho J.-H.; Zhu M.; Anwar A.; Kamhoua C.; Singh M. | B57: Wan, Zelin (59452758700); Cho, Jin-Hee (55474140000); Zhu, Mu (57219693663); Anwar, Ahmed (55838805200); Kamhoua, Charles (36918490600); Singh, Munindar (36515667700) | C57: 59452758700; 55474140000; 57219693663; 55838805200; 36918490600; 36515667700 | D57: Optimizing Effectiveness and Defense of Drone Surveillance Missions via Honey Drones | E57: 2024 | F57: ACM Transactions on Internet Technology | G57: 24 | H57: 4 | I57: 22 | M57: 10.1145/3701233 | N57: https://www.scopus.com/inward/record.uri?eid=2-s2.0-85210741444&doi=10.1145%2f3701233&partnerID=40&md5=ba232ac90f28fa2464e8a726e254721a | O57: This work aims to develop a surveillance mission system using unmanned aerial vehicles (UAVs) or drones when Denial-of-Service (DoS) attacks are present to disrupt normal operations for mission systems. In particular, we introduce the concept of cyber deception using honey drones (HDs) to protect the mission system from DoS attacks. HDs exhibit fake vulnerabilities and employ stronger signal strengths to lure DoS attacks, unlike the legitimate drones called mission drones (MDs) deployed for mission execution. This research formulates an optimization problem to identify an optimal set of signal strengths of HDs and MDs to best prevent the system from DoS attacks while maximizing mission performance under the resource constraints of UAVs. To solve this optimization problem, we leverage deep reinforcement learning (DRL) to achieve these multiple objectives of the mission system concerning system security and performance. Particularly, for efficient and effective parallel processing in DRL, we utilize a DRL algorithm called the Asynchronous Advantage Actor-Critic (A3C) algorithm to model attack-defense interactions. We employ a physical engine-based simulation testbed to consider realistic scenarios and demonstrate valid findings from the realistic testbed. The extensive experiments proved that our HD-based approach could achieve up to a 32% increase in mission completion, a 20% reduction in energy consumption, and a 62% decrease in attack success rates compared to existing defense strategies. © 2024 held by the owner/author(s). | P57: Additional Key Words and PhrasesDefensive deception; deep reinforcement learning; mission effectiveness; unmanned aerial vehicle | Q57: 2-s2.0-85210741444
A58: Hassler S.C.; Mughal U.A.; Ismail M. | B58: Hassler, Samuel Chase (57211322960); Mughal, Umair Ahmad (58828947200); Ismail, Muhammad (55310847800) | C58: 57211322960; 58828947200; 55310847800 | D58: Cyber-Physical Intrusion Detection System for Unmanned Aerial Vehicles | E58: 2024 | F58: IEEE Transactions on Intelligent Transportation Systems | G58: 25 | H58: 6 | J58: 6106 | K58: 6117 | L58: 11 | M58: 10.1109/TITS.2023.3339728 | N58: https://www.scopus.com/inward/record.uri?eid=2-s2.0-85181566533&doi=10.1109%2fTITS.2023.3339728&partnerID=40&md5=424a8abab1318b7d2dfb7fce4bd57057 | O58: The increasing reliance on unmanned aerial vehicles (UAVs) has escalated the associated cyber risks. While machine learning has enabled intrusion detection systems (IDSs), current IDSs do not incorporate cyber-physical UAV features, which limits their detection performance. Additionally, the lack of public UAV's cyber and physical datasets to develop IDS hinders further research. Therefore, this paper proposes a novel IDS fusing UAV cyber and physical features to improve detection capabilities. First, we developed a testbed that includes UAV, controller, and data collection tools to execute cyber-attacks and gather cyber and physical data under normal and attack conditions. We made this dataset publicly available. The dataset covers a range of cyber-attacks including denial-of-service, replay, evil twin, and false data injection attacks. Then, machine learning-based IDSs fusing cyber and physical features were trained to detect cyber-attacks using support vector machines, feedforward neural networks, recurrent neural networks with long short-term memory cells, and convolutional neural networks. Extensive experiments were conducted on varying complexity and range of attack training data to explore whether (a) fusion of cyber and physical features enhances detection performance compared to cyber or physical features alone, (b) fusion enhances detection when IDS is trained on a single attack type and tested on unseen attacks of varying complexity, (c) fusion enhances performance when the range of attack training data increases and models are tested on unseen attacks. Answering these research questions provides insights into IDS capabilities using cyber, physical, and cyber-physical features under different conditions. © 2000-2011 IEEE. | P58: and machine learning; cyber-physical systems; intrusion detection systems; UAVs | Q58: 2-s2.0-85181566533
A59: Dai Z. | B59: Dai, Zhenjun (59250338000) | C59: 59250338000 | D59: Image acquisition technology for unmanned aerial vehicles based on YOLO - Illustrated by the case of wind turbine blade inspection | E59: 2024 | F59: Systems and Soft Computing | G59: 6 | I59: 200126 | M59: 10.1016/j.sasc.2024.200126 | N59: https://www.scopus.com/inward/record.uri?eid=2-s2.0-85200637466&doi=10.1016%2fj.sasc.2024.200126&partnerID=40&md5=5e97f9586c0dd1b9b744ffae00a1cd64 | O59: Wind energy, as a renewable energy source, is becoming increasingly important. The maintenance and damage detection of wind turbine blades are particularly crucial. For this purpose, the study aims to optimize the You Only Look Once (YOLO) processing algorithm for drone images to improve the detection efficiency. Firstly, the damage images captured by drones are preprocessed and optimized, including deblurring, noise reduction, and image enhancement. Subsequently, the YOLOv5 model is improved in terms of structure and regression function, and a novel damage detection model is proposed. The research results indicated that the minimum loss function value of the improved model was 2.75, the average accuracy was 95 %, and the highest intersection over union was 91 %. After simulation testing, the detection effect of this model on abrasion, crackle, edge cracking, and coating peeling images was significantly better than other models in the same series. Its average time was as short as 2.43 s, reaching a maximum frame rate of 35.46. From this, the combination of drone image technology and improved image processing algorithm has a positive impact on improving the operational efficiency and safety of wind turbine blades. Compared with the traditional methods, the proposed model has significant advantages in terms of accuracy and real-time performance of damage detection, providing a new technical means for efficient maintenance of wind turbines. Meanwhile, the method shows high robustness and reliability in different types of damage detection, demonstrating the extensive potential in practical applications. © 2024 | P59: Image detection; Intersection over union; Preprocessing; Wind turbine blade; YOLO | Q59: 2-s2.0-85200637466
A60: Ihekoronye V.U.; Ajakwe S.O.; Lee J.M.; Kim D.-S. | B60: Ihekoronye, Vivian Ukamaka (57415267500); Ajakwe, Simeon Okechukwu (57414321100); Lee, Jae Min (57194451001); Kim, Dong-Seong (55586876300) | C60: 57415267500; 57414321100; 57194451001; 55586876300 | D60: DroneGuard: An Explainable and Efficient Machine Learning Framework for Intrusion Detection in Drone Networks | E60: 2024 | F60: IEEE Internet of Things Journal | M60: 10.1109/JIOT.2024.3519633 | N60: https://www.scopus.com/inward/record.uri?eid=2-s2.0-85213054023&doi=10.1109%2fJIOT.2024.3519633&partnerID=40&md5=a126b746f2a32896bd64145dd8d2023c | O60: Vulnerabilities in drone networks stem from the reliance on GPS and wireless communication technologies, combined with the lack of robust security mechanisms. This study proposes DroneGuard, a comprehensive cybersecurity framework leveraging supervised machine learning (ML) and explainable artificial intelligence (XAI) to detect intrusions and provide insights into the decision-making process of the security model. We explored various feature selection techniques to design a lightweight model suitable for the resource constraints of drones. Additionally, the synthetic minority oversampling technique (SMOTE) is employed to balance target class distribution and mitigate performance degradation, while randomized search cross-validation (RSCV) aids in selecting optimal hyperparameters for model training. Simulation experiments were conducted using a real-time GPS dataset for autonomous vehicles and a cybersecurity dataset containing variants of DoS attacks to evaluate the models' performance. Comparison with four ML models using essential evaluation metrics validated the robust performance of the Decision Tree model, which detected spoofed GPS signals and DoS attacks with high accuracy, low computational complexity, and minimal false alarm rates. Furthermore, the SHapley Additive exPlanation (SHAP) provides intuitive visual explanations of important features contributing to the detection and classification of both GPS spoofing and DoS attacks. Therefore, DroneGuard offers effective and interpretable security solutions for enhanced drone application and adoption. © 2014 IEEE. | P60: Cybersecurity; Denial of Service Attacks; Drone Network; Feature Selection Technique; GPS Spoofing Attacks; Intrusion Detection; Machine Learning Models; Randomized Search Cross Validation; UAVs; XAI | Q60: 2-s2.0-85213054023
A61: Polasi S.; Vajjha H.G.V. | B61: Polasi, Sushma (59476455200); Vajjha, Hara Gopal Venkata (59476455300) | C61: 59476455200; 59476455300 | D61: Secure Drone Communications using MQTT protocol | E61: 2024 | F61: International Journal of Computational and Experimental Science and Engineering | G61: 10 | H61: 4 | J61: 1282 | K61: 1289 | L61: 7 | M61: 10.22399/ijcesen.685 | N61: https://www.scopus.com/inward/record.uri?eid=2-s2.0-85212295579&doi=10.22399%2fijcesen.685&partnerID=40&md5=0ae515b84abd3002dc0e2ab1412d005e | O61: With the revolutionary change in emerging technologies, the usage of drones or unmanned aerial vehicles (UAV) has exponentially increased in different sectors like Industry, healthcare, military, agriculture, real estate, manufacturing, logistics, energy and many more utilities. This rapid growth creates a concern for the secure communication between the internal communication modules and the ground based computer system used for controlling the UAV. Intruder can hack into the device and attack the internal communication device with the injection of the malicious code which can lead to the malfunction of the aircraft. Security issues related to the communication between the internal modules of the drone and the ground based computer system is of major concern and is crucial. UAVs have to operate in constrained networks with limited bandwidth. In such a constrained environment MQTT protocol can be an excellent protocol. No cryptographic techniques are used to retain the simplicity and the light weight of the MQTT protocol. This contributes for the large scope for emerging with new solutions in the protection issues of MQTT communications. This paper mainly focuses on Armstrong number encryption standard algorithm for providing a computationally simple yet a secure and strong algorithm for UAVs encryption and decryption process on the communication links using MQTT protocol. © IJCESEN. | P61: Cyber security; Drones security; Encryption algorithm; MQTT protocol; UAV secure communications | Q61: 2-s2.0-85212295579
A62: Titouna C.; Nait-Abdesselam F. | B62: Titouna, Chafiq (55639343800); Nait-Abdesselam, Farid (55952572800) | C62: 55639343800; 55952572800 | D62: A Convolutional Neural Network-based Approach For Image Analysis and Injection Detection | E62: 2024 | F62: Proceedings - IEEE International Conference on Advanced Video and Signal-Based Surveillance, AVSS | H62: 2024 | M62: 10.1109/AVSS61716.2024.10672581 | N62: https://www.scopus.com/inward/record.uri?eid=2-s2.0-85208434464&doi=10.1109%2fAVSS61716.2024.10672581&partnerID=40&md5=4a10c214b38a0b5bf855dbecde74953a | O62: Due to their usefulness in smart cities and other civilian uses, drones are becoming increasingly popular. With the ability to be organized into networks, they can be used to gather various kinds of data, including images and videos with multimedia characteristics, and then forward it to processing centers for additional handling. They also become a fresh target for a variety of attacks, such as GPS spoofing, denial of service, and false data injection. It is therefore vital and required to create new systems and protection mechanisms against these threats. In this research, we highlight the risk associated with the so-called False Data Injection (FDI) and present a deep learning-based approach for detecting it. An injection of misleading data into the data (images) gathered by the drones is regarded as a serious and potent attack that has the potential to significantly change a final judgment made by the processing center. Our strategy uses deep learning for image analysis and classification in order to thwart this attack. Using Nearest Neighbor Interpolation (NNI) to scale the incoming image to match the classifier, we next feed the image to a Convolutional Neural Network (CNN) for image classification. Finally, we use the Mahalanobis Distance to compare each class of classification results to a neighborhood. Our solution performs well, irrespective of image size, as evidenced by numerical findings on the current dataset, which show an accuracy of 97.71%, a precision of 96.69%, a recall of 94.33%, and an F-score of 0.941%. © 2024 IEEE. | P62: Convolutional Neural Network; False Data Injection; Unmanned Aerial Vehicles | Q62: 2-s2.0-85208434464
A63: Han S.; Wang M.; Duan J.; Zhang J.; Li D. | B63: Han, Songyue (57491691500); Wang, Mingyu (57867257300); Duan, Junhong (59489058300); Zhang, Jialong (57202339479); Li, Dongdong (56226705300) | C63: 57491691500; 57867257300; 59489058300; 57202339479; 56226705300 | D63: Research on Unmanned Aerial Vehicle Emergency Support System and Optimization Method Based on Gaussian Global Seagull Algorithm | E63: 2024 | F63: Drones | G63: 8 | H63: 12 | I63: 763 | M63: 10.3390/drones8120763 | N63: https://www.scopus.com/inward/record.uri?eid=2-s2.0-85213225035&doi=10.3390%2fdrones8120763&partnerID=40&md5=8792130796d69234a903de7410d9f97a | O63: In emergency rescue scenarios, drones can be equipped with different payloads as needed to aid in tasks such as disaster reconnaissance, situational awareness, communication support, and material assistance. However, rescue missions typically face challenges such as limited reconnaissance boundaries, heterogeneous communication networks, complex data fusion, high task latency, and limited equipment endurance. To address these issues, an unmanned emergency support system tailored for emergency rescue scenarios is designed. This system leverages 5G edge computing technology to provide high-speed and flexible network access along with elastic computing power support, reducing the complexity of data fusion across heterogeneous networks. It supports the control and data transmission of drones through the separation of the control plane and the data plane. Furthermore, by applying the Tammer decomposition method to break down the system optimization problem, the Global Learning Seagull Algorithm for Gaussian Mapping (GLSOAG) is proposed to jointly optimize the system’s energy consumption and latency. Through simulation experiments, the GLSOAG demonstrates significant advantages over the Seagull Optimization Algorithm (SOA), Particle Swarm Optimization (PSO), and Beetle Antennae Search Algorithm (BAS) in terms of convergence speed, optimization accuracy, and stability. The system optimization approach effectively reduces the system’s energy consumption and latency costs. Overall, our work alleviates the pain points faced in rescue scenarios to some extent. © 2024 by the authors. | P63: 5G; emergency support; Gaussian global seagull algorithm; mobile edge computing; resource optimization method; UAV | Q63: 2-s2.0-85213225035
A64: Rimoli G.P.; Palmieri F.; Ficco M. | B64: Rimoli, Gennaro Pio (58973935400); Palmieri, Francesco (7103111550); Ficco, Massimo (14021031600) | C64: 58973935400; 7103111550; 14021031600 | D64: Synthetic threat Dataset Generation by UAV fleet Simulation | E64: 2024 | F64: Proceedings of the International Defense and Homeland Security Simulation Workshop, DHSS | G64: 2024-September | I64: 002 | M64: 10.46354/i3m.2024.dhss.002 | N64: https://www.scopus.com/inward/record.uri?eid=2-s2.0-85210589564&doi=10.46354%2fi3m.2024.dhss.002&partnerID=40&md5=b348d34afbe2c3436ee7fff027c28614 | O64: In the coming years, institutions, such as law enforcement, rescue agencies, and companies, will increasingly use drone fleets to support inspection, logistics, and surveillance applications, in scenarios that may also be highly sensitive for managed data, performed tasks, or the contexts in which they operate. Security-by-design and machine learning-based models may represent the main paradigms for the design of systems resistant to cyber attacks. However, the lack of open datasets and simulation frameworks may represent the main challenge in this direction. Therefore, this paper aims to propose an open source software stack and a schema for creating synthetic standard missions, attacks, and component failures, for the generation of scenarios and data useful for addressing security threats against drone fleets. The produced data set may be used to implement machine learning-based security intrusion detectors on a centralized ground station, as well as on-board agents that may be deployed on a drone to detect anomalous behaviors of compromised drones of the fleet in real time. © 2024 The Authors. | P64: Cyber security; drone fleet simulation; Machine Learning; TinyML; UAV threat data generation; UAV threat dataset | Q64: 2-s2.0-85210589564
A65: Zhou R.; Almustafa M.K.; Nehdi M.L.; Su H. | B65: Zhou, Renlian (57203532030); Almustafa, Monjee K. (57218162523); Nehdi, Moncef L. (7004176002); Su, Huaizhi (8261698000) | C65: 57203532030; 57218162523; 7004176002; 8261698000 | D65: Automated localization of dike leakage outlets using UAV-borne thermography and YOLO-based object detectors | E65: 2024 | F65: ISPRS Journal of Photogrammetry and Remote Sensing | G65: 218 | J65: 551 | K65: 573 | L65: 22 | M65: 10.1016/j.isprsjprs.2024.09.039 | N65: https://www.scopus.com/inward/record.uri?eid=2-s2.0-85205360346&doi=10.1016%2fj.isprsjprs.2024.09.039&partnerID=40&md5=07bb1ade0485406e7a29984de77e43b6 | O65: Leakage-induced soil erosion poses a major threat to dike failure, particularly during floods. Timely detection and notification of leakage outlets to dike management are crucial for ensuring dike safety. However, manual inspection, the current main approach for identifying leakage outlets, is costly, inefficient, and lacks spatial coverage. To achieve efficient and automatic localization of dike leakage outlets, an innovative strategy combining drones, infrared thermography, and deep learning is presented. Drones are employed for dikes’ surface sensing. Real-time images from these drones are sent to a server where well-trained detectors are deployed. Once a leakage outlet is detected, alarming information is remotely sent to dike managers. To realize this strategy, 4 thermal imagers were employed to image leaking outlets of several models and actual dikes. 9,231 hand-labeled thermal images with 13,387 leaking objects were selected for analysis. 19 detectors were trained using transfer learning. The best detector achieved a mean average precision of 95.8 % on the challenging test set. A full-scale embankment was constructed for leakage outlet detection tests. Various field tests confirmed the efficiency of the proposed leakage outlet localization method. In some tough conditions, the trained detector also evidently outperformed manual judgement. Results indicate that under typical circumstances, the localization error of the proposed method is within 5 m, demonstrating its practical reliability. Finally, the influencing factors and limits of the suggested strategy are thoroughly examined. © 2024 International Society for Photogrammetry and Remote Sensing, Inc. (ISPRS) | P65: Convolutional neural network; Dike; Drone; Infrared thermography; Leakage; Object detection; River embankment | Q65: 2-s2.0-85205360346
A66: Marchetti E.; Waheed T.; Calabrò A. | B66: Marchetti, Eda (16242101500); Waheed, Tauheed (58759828400); Calabrò, Antonello (36702488800) | C66: 16242101500; 58759828400; 36702488800 | D66: Cybersecurity Testing in Drones Domain: A Systematic Literature Review | E66: 2024 | F66: IEEE Access | G66: 12 | J66: 171166 | K66: 171184 | L66: 18 | M66: 10.1109/ACCESS.2024.3495994 | N66: https://www.scopus.com/inward/record.uri?eid=2-s2.0-85209639237&doi=10.1109%2fACCESS.2024.3495994&partnerID=40&md5=75964fb9f29b937d5489030334cb7d73 | O66: The widespread use of unmanned aerial vehicles (UAVs) drone cybersecurity testing is becoming an emerging and evolving research area for cybersecurity and privacy issues avoidance and prevention. This paper contributes to guiding the research activity by systematically surveying the commonly adopted solutions and proposals for cybersecurity testing in the drone research domain. It highlights the research challenges and issues, classifies the current proposal, methodologies, and techniques, and suggests future directions. After gathering a collection of papers using automated inquiry of well-known digital libraries and snowballing techniques, a classification schema has been proposed and applied to the identified research works. Furthermore, research questions have been identified and answered through the performed classification. The paper provides an outlook on cybersecurity testing in drone environments. It also lists current criticalities, challenges, gaps, and future directions useful to improve drone quality and increase cybersecurity. The analysis reveals that the collected results point to a meaningful evolution and innovative approaches in cybersecurity testing within current research activities. © 2013 IEEE. | P66: cybersecurity; Drones; testing; UAV | Q66: 2-s2.0-85209639237
A67: Corraro G.; Corraro F.; Flora A.; Cuciniello G.; Garbarino L.; Senatore R. | B67: Corraro, Gianluca (56595204600); Corraro, Federico (22949701300); Flora, Andrea (59441341400); Cuciniello, Giovanni (24398572800); Garbarino, Luca (37046924400); Senatore, Roberto (54791434700) | C67: 56595204600; 22949701300; 59441341400; 24398572800; 37046924400; 54791434700 | D67: Dual-Frequency Multi-Constellation Global Navigation Satellite System/Inertial Measurements Unit Tight Hybridization for Urban Air Mobility Applications | E67: 2024 | F67: Aerospace | G67: 11 | H67: 11 | I67: 955 | M67: 10.3390/aerospace11110955 | N67: https://www.scopus.com/inward/record.uri?eid=2-s2.0-85210443677&doi=10.3390%2faerospace11110955&partnerID=40&md5=ee4e995050f926e8bb70541cc1eff34b | O67: A global navigation satellite system (GNSS) for remotely piloted aircraft systems (RPASs) positioning is essential, thanks to the worldwide availability and continuity of this technology in the provision of positioning services. This makes the GNSS technology a critical element as malfunctions impacting on the determination of the position, velocity and timing (PVT) solution could determine safety issues. Such an aspect is particularly challenging in urban air mobility (UAM) scenarios, where low satellite visibility, multipath, radio frequency interference and cyber threats can dangerously affect the PVT solution. So, to meet integrity requirements, GNSS receiver measurements are augmented/fused with other aircraft sensors that can supply position and/or velocity information on the aircraft without relying on any other satellite and/or ground infrastructures. In this framework, in this paper, the algorithms of a hybrid navigation unit (HNU) for UAM applications are detailed, implementing a tightly coupled sensor fusion between a dual-frequency multi-constellation GNSS receiver, an inertial measurements unit and the barometric altitude from an air data computer. The implemented navigation algorithm is integrated with autonomous fault detection and exclusion of GPS/Galileo/BeiDou satellites and the estimation of navigation solution integrity/accuracy (i.e., protection level and figures of merit). In-flight tests were performed to validate the HNU functionalities demonstrating its effectiveness in UAM scenarios even in the presence of cyber threats. In detail, the navigation solution, compared with a real-time kinematic GPS receiver used as the reference centimetre-level position sensor, demonstrated good accuracy, with position errors below 15 m horizontally and 10 m vertically under nominal conditions (i.e., urban scenarios characterized by satellite low visibility and multipath). It continued to provide a valid navigation solution even in the presence of off-nominal events, such as spoofing attacks. The cyber threats were correctly detected and excluded by the system through the indication of the valid/not valid satellite measurements. However, the results indicate a need for fine-tuning the EKF to improve the estimation of figures of merit and protection levels associated to the navigation solution during the cyber-attacks. In contrast, solution accuracy and integrity indicators are well estimated in nominal conditions. © 2024 by the authors. | P67: dual-frequency multi-constellation global navigation satellite system; fault detection and exclusion; hybrid navigation system; in-flight validation; inertial measurement unit; tightly coupled sensor fusion; urban air mobility | Q67: 2-s2.0-85210443677
A68: Bakhtiiarov D.; Chumachenko B.; Lavrynenko O.; Antonov V. | B68: Bakhtiiarov, Denys (57193068955); Chumachenko, Bohdan (58677498400); Lavrynenko, Oleksandr (57193057763); Antonov, Veniamin (58698807300) | C68: 57193068955; 58677498400; 57193057763; 58698807300 | D68: Evaluating The UAV's Communication Channels Energy Availability In The Context Of Enemy Electronic Countermeasures | E68: 2024 | F68: 2024 IEEE 7th International Conference on Actual Problems of Unmanned Aerial Vehicles Development, APUAVD 2024 - Proceedings | J68: 159 | K68: 164 | L68: 5 | M68: 10.1109/APUAVD64488.2024.10765900 | N68: https://www.scopus.com/inward/record.uri?eid=2-s2.0-85213349250&doi=10.1109%2fAPUAVD64488.2024.10765900&partnerID=40&md5=26278f6d8ba6158f7bd3ee211e2b8b6a | O68: This article compares the energy availability of radio communications in drones and other unmanned aerial vehicles. According to the research, all radio communication technologies under consideration are susceptible to radio jamming via the use of electronic warfare. Only discrete and broadband modulation schemes without interference-resistant coding can provide radio jamming energy efficiency. In discrete and broadband systems, this efficiency may be guaranteed to some extent using interference-resistant coding. The most promising solutions are those based on broadband communication systems with the greatest degree of interference resistance, according to analytical estimations of the radio jamming coefficient. These systems are exceptionally reliable communications that fulfill the criteria for protection against radio reconnaissance, secrecy, and bandwidth because various techniques of interference-resistant coding are used to increase protection against signal interference. © 2024 IEEE. | P68: broadband modulation system; electronic warfare; energy efficiency; radio jamming coefficient; radio signal; unmanned aerial vehicle | Q68: 2-s2.0-85213349250
A69: Yoo J.D.; Kim H.; Kim H.K. | B69: Yoo, Jeong Do (59068097600); Kim, Haerin (58070714800); Kim, Huy Kang (7410133266) | C69: 59068097600; 58070714800; 7410133266 | D69: GUIDE: GAN-based UAV IDS Enhancement | E69: 2024 | F69: Computers and Security | G69: 147 | I69: 104073 | M69: 10.1016/j.cose.2024.104073 | N69: https://www.scopus.com/inward/record.uri?eid=2-s2.0-85202345878&doi=10.1016%2fj.cose.2024.104073&partnerID=40&md5=719dbab03189617a29f65933fdac0234 | O69: With the development of information technology, many devices are connected and automated by networks. Unmanned Areal Vehicles (UAVs), commonly known as drones, are one of the most popular devices that can perform various tasks. However, the risk of cyberattacks on UAVs is increasing as UAV utilization grows. These cyberattacks can cause serious safety problems, such as crashes. Therefore, it is essential to detect these attacks and take countermeasures. As a countermeasure, intrusion detection system (IDS) is widely adopted. To implement IDS for UAVs, it should be lightweight and be able to detect unknown attacks as a requirement. We propose GAN-based UAV IDS Enhancement (GUIDE) to meet the requirements. The GUIDE employs a generative adversarial network (GAN) for integer-valued sequence data augmentation to enhance an IDS's performance on known and unknown attacks. We used five GANs: SeqGAN, MaskGAN, RankGAN, StepGAN, and LeakGAN; we used four non-learning augmentation methods for the comparative experiment: oversampling, undersampling, noise addition, and random generation. The experimental results demonstrated that the synthetic data generated by GANs improved the detection of known attacks (up to 37 percentage points) and unknown attacks (up to 30 percentage points) while maintaining stable IDS performance. We also analyzed the synthetic data by employing Jensen–Shannon divergence, synthetic ranking agreement, and visualization; we confirmed that the synthetic data contained the characteristics of real data and could be used for training the IDS. © 2024 Elsevier Ltd | P69: Cybersecurity; Data augmentation; Drone; GAN; IDS; Intrusion detection system; MAVLink; UAV | Q69: 2-s2.0-85202345878
A70: Babu C.V.S.; Pal A. | B70: Babu, C.V. Suresh (58533494800); Pal, Abhinaba (58597137900) | C70: 58533494800; 58597137900 | D70: Enhancing Security for Unmanned Aircraft Systems in IoT Environments: Defense Mechanisms and Mitigation Strategies | E70: 2024 | F70: Unmanned Aircraft Systems | J70: 429 | K70: 476 | L70: 47 | M70: 10.1002/9781394230648.ch11 | N70: https://www.scopus.com/inward/record.uri?eid=2-s2.0-85213777982&doi=10.1002%2f9781394230648.ch11&partnerID=40&md5=725fb2211a11763873f6737b0ee3de49 | O70: The rapid evolution of Next Generation Transportation and Unmanned Aircraft Systems (UAS) in the Internet of Things (IoT) paradigm has introduced exciting possibilities for various industries, including military operations, surveillance, logistics, and agriculture. However, this advancement also brings forth a multitude of security challenges that demand immediate attention. Unauthorized access represents a significant threat, where malicious actors may attempt to gain illicit control over UAS control systems or exploit vulnerabilities in communication links. Past incidents, like the spoofing attack on a Parrot AR. Drone, underscore the real possibility of such unauthorized access, enabling adversaries to manipulate flight paths or disrupt operations with relative ease. Additionally, the generation and transmission of substantial data by IoT-enabled UAS create another vulnerability, allowing for interception and manipulation of critical information. This includes telemetry, sensor readings, and video feeds, posing a serious risk of false information dissemination to the drone operator or mission control, impacting decision-making and overall mission success. Addressing these issues is imperative to ensure the secure integration and operation of UAS within the IoT ecosystem. This chapter aims to explore the unique security concerns associated with UAS in complex, heterogeneous, and highly distributed IoT environments. It will delve into the vulnerabilities and threats faced by UAS, such as signal tampering, jamming, physical attacks, GPS spoofing, laser-based attacks, and protocol abuses and scrutinize their respective mitigation tactics which also end up being capriciously effective depending on the operating environment. © 2025 Scrivener Publishing LLC. | P70: GPS spoofing attacks; Internet of Things (IoT); laser-based attacks; security challenges; trust architectures; unmanned aircraft systems (UAS) | Q70: 2-s2.0-85213777982
A71: Rathinasamy D.; Sivaramakrishnan R.; Pavithra R.; Kaliappan V.K. | B71: Rathinasamy, Dhivya (57212156747); Sivaramakrishnan, R. (57370078800); Pavithra, R. (58576469100); Kaliappan, Vishnu Kumar (24829297500) | C71: 57212156747; 57370078800; 58576469100; 24829297500 | D71: Safety and security challenges in implementing urban air mobility | E71: 2024 | F71: Urban Air Mobility: Intelligent, Safe and Sustainable Systems for Future Transportation | J71: 211 | K71: 238 | L71: 27 | N71: https://www.scopus.com/inward/record.uri?eid=2-s2.0-85203350895&partnerID=40&md5=9694cb74679db47ca940dc9e1a843a01 | O71: Urban air mobility (UAM) is a new concept of transportation that has the potential to revolutionize urban mobility by providing efficient, fast, and environmentally friendly solutions for urban transportation. This chapter provides a comprehensive overview of UAM, its potential benefits, and challenges. It explores the need for UAM and the challenges it presents in terms of safety and security. The chapter discusses the different types of security measures, including passive, preventive, active, and destructive measures, and emphasizes the importance of comprehensive measures to address these challenges. Additionally, this chapter highlights the limitations of existing research on UAM and the need for further studies to fully understand the implications of UAM implementation in urban areas. While UAM has the potential to revolutionize urban transportation, it also presents significant challenges that must be addressed through continued research, planning, and collaboration between stakeholders to ensure its safe and sustainable implementation in the future. © 2024 River Publishers. All rights reserved. | P71: Cyber-attacks; Detection methods; Unmanned aerial vehicle | Q71: 2-s2.0-85203350895
A72: Tesfay A.A.; Aouladhadj D.; Deniau V.; Gransart C.; Dufour M.; Sondi P. | B72: Tesfay, Angesom Ataklity (57219594190); Aouladhadj, Driss (57818850200); Deniau, Virginie (24466454100); Gransart, Christophe (55917439900); Dufour, Mickael (59474358400); Sondi, Patrick (23398391400) | C72: 57219594190; 57818850200; 24466454100; 55917439900; 59474358400; 23398391400 | D72: Smart Jamming: Deep Learning-Based UAVs Neutralization System | E72: 2024 | F72: Proceedings of the International Symposium on Electromagnetic Compatibility, EMC Europe | H72: 2024 | J72: 380 | K72: 384 | L72: 4 | M72: 10.1109/EMCEurope59828.2024.10722367 | N72: https://www.scopus.com/inward/record.uri?eid=2-s2.0-85212217560&doi=10.1109%2fEMCEurope59828.2024.10722367&partnerID=40&md5=479f842ab680fcb003701dfc4ae3abc8 | O72: Recently the proliferation of unmanned aerial vehicles (UAVs) has emerged as a pressing concern, attributed to the accessibility of capable drones and the surge in incidents involving unauthorized UAVs flying over restricted areas, such as airports, stadiums, military bases, etc. Consequently, the development and deployment of drone jamming techniques have been proposed to address this evolving threat, particularly by law enforcement agencies. However, these jamming technologies require high transmitted power and risk interference with other communications operating within the same industrial, scientific, and medical (ISM) band. This paper introduces a smart jamming technique to neutralize UAVs threats. The proposed approach uses radio frequency (RF) analysis and deep learning techniques to identify the drone model and generate tailored jamming signals to minimize overall power consumption to neutralize the target drone. Simulation results show that the proposed approach outperforms other jamming techniques. The proposed approach attains successful jamming at low jammer-to-signal ratios (JSR) as compared to other jammers, as a result, less transmitted power is required to reach the same jamming performance as the other jamming technique. © 2024 IEEE. | P72: deep learning; smart jamming; UAVS system | Q72: 2-s2.0-85212217560
A73: Bayrak S. | B73: Bayrak, Sengul (56526714700) | C73: 56526714700 | D73: Unveiling intrusions: explainable SVM approaches for addressing encrypted Wi-Fi traffic in UAV networks | E73: 2024 | F73: Knowledge and Information Systems | G73: 66 | H73: 11 | J73: 6675 | K73: 6695 | L73: 20 | M73: 10.1007/s10115-024-02181-9 | N73: https://www.scopus.com/inward/record.uri?eid=2-s2.0-85198653149&doi=10.1007%2fs10115-024-02181-9&partnerID=40&md5=c4a05a415e9312abb08a4f218d2df0a8 | O73: Unmanned aerial vehicles (UAVs), also known as drones, have become instrumental in various domains, including agriculture, geographic information systems, media, logistics, security, and defense. These UAVs often rely on wireless communication networks for data transmission, making them vulnerable to cyberattacks. To address these challenges, it is necessary to detect potential threats by analyzing the encrypted Wi-Fi traffic data generated by UAVs. This study aimed to develop a linear SVM model that is enhanced with explainable artificial intelligence (XAI) techniques and fine-tuned using Bayesian optimization for intrusion detection systems (IDSs); the model is specifically designed to identify malware threats targeting UAVs. This research utilized encrypted Wi-Fi traffic data derived from three different UAV networks, namely, Parrot Bebop 1, DBPower UDI, and DJI Spark, while considering unidirectional and bidirectional communication flow modes. SVM-based intrusion detection models have been modeled on these datasets, identified their key features using the local interpretable model-agnostic explanations (LIME) technique, and conducted a cost analysis of the proposed modeling approach. The incorporation of the LIME method enabled to highlight the features that are highly indicative of cyberattacks and provided valuable insights into the importance of each feature in the context of intrusion detection. In conclusion, this interpretable IDS model, fine-tuned with Bayesian optimization, demonstrated its superiority over the state-of-the-art methods, proving its efficacy in detecting and mitigating threats to UAVs while offering a cost-effective solution. © The Author(s) 2024. | P73: Encrypted Wi-Fi traffic classification; Explainable artificial intelligence; Intrusion detection system; Support vector machine; Unmanned aerial vehicles | Q73: 2-s2.0-85198653149
A74: Shah I.A.; Jhanjhi N.Z. | B74: Shah, Imdad Ali (57923320900); Jhanjhi, Noor Zaman (36088700700) | C74: 57923320900; 36088700700 | D74: Cybersecurity issues and challenges in the drone industry | E74: 2024 | F74: Cybersecurity Issues and Challenges in the Drone Industry | J74: 1 | K74: 573 | L74: 572 | M74: 10.4018/979-8-3693-0774-8 | N74: https://www.scopus.com/inward/record.uri?eid=2-s2.0-85191256888&doi=10.4018%2f979-8-3693-0774-8&partnerID=40&md5=6862c71754a665f0eee0fc57b1e4245e | O74: Cybersecurity Issues and Challenges in the Drone Industry is a comprehensive exploration of the critical cybersecurity problems faced by the rapidly expanding drone industry. With the widespread adoption of drones in military, commercial, and recreational sectors, the need to address cybersecurity concerns has become increasingly urgent. In this book, cybersecurity specialists collaborate to present a multifaceted approach to tackling the unique challenges posed by drones. They delve into essential topics such as establishing robust encryption and authentication systems, conducting regular vulnerability assessments, enhancing software security, advocating industry-wide standards and best practices, and educating drone users about the inherent cybersecurity risks. As drones, or unmanned aerial vehicles (UAVs), gain popularity and are deployed for various applications, ranging from aerial photography and surveillance to delivery services and infrastructure inspections, this book emphasizes the criticality of safeguarding the security, integrity, and privacy of drone systems and the data they handle. It highlights the growing vulnerability of drones to cybersecurity threats as these devices become increasingly connected and integrated into our everyday lives. This book is an invaluable resource for drone manufacturers, government agencies, regulators, cybersecurity professionals, and academia and research institutions invested in understanding and mitigating the cybersecurity risks in the drone industry. It provides insights into the use of advanced technologies, such as artificial intelligence, in addressing security issues, the importance of cyber-physical systems security, and the development of efficient and secure models for image detection using deep learning. Furthermore, the book explores the security concerns associated with AI-based drones in smart cities and offers guidelines for measuring appropriate security measures. Cybersecurity Issues and Challenges in the Drone Industry serves as a roadmap for protecting the integrity and resilience of drone systems in the face of evolving cybersecurity threats. By promoting a collaborative and proactive approach, this book equips stakeholders with the knowledge and strategies necessary to ensure the safe and secure operation of drones in today's interconnected world. © 2024 by IGI Global. All rights reserved. | Q74: 2-s2.0-85191256888
A75: Yang F.; Wang C.; Xiong J.; Deng N.; Zhao N.; Li Y. | B75: Yang, Fangtao (57215128519); Wang, Chao (54400510500); Xiong, Jun (55326779700); Deng, Na (55322607800); Zhao, Nan (45562028800); Li, Yonghui (57218530399) | C75: 57215128519; 54400510500; 55326779700; 55322607800; 45562028800; 57218530399 | D75: UAV-Enabled Robust Covert Communication Against Active Wardens | E75: 2024 | F75: IEEE Transactions on Vehicular Technology | G75: 73 | H75: 6 | J75: 9159 | K75: 9164 | L75: 5 | M75: 10.1109/TVT.2024.3360998 | N75: https://www.scopus.com/inward/record.uri?eid=2-s2.0-85184324852&doi=10.1109%2fTVT.2024.3360998&partnerID=40&md5=fdd4d57e75da137373fd83672661ec2c | O75: This correspondence investigates the robust unmanned aerial vehicle (UAV) enabled covert communication system with active ground wardens of collusive detection and location uncertainty. The three-dimensional (3D) trajectory and transmit power of UAV are jointly optimized to maximize the average covert transmission rate subject to the worst-case covertness constraint. The problem is intractable due to its nonconvexity and semi-positive definite matrix constraint, and an iterative suboptimal algorithm is proposed based on the block coordinate descent, S-procedure and successive convex optimization to tackle it. Numerical results demonstrate that the proposed scheme is effective and robust for UAV-enabled covert communications against active wardens. © 2024 IEEE. Personal use is permitted, but republication/redistribution requires IEEE permission. | P75: Active detection; covert communication; covert transmission rate; unmanned aerial vehicle (UAV) | Q75: 2-s2.0-85184324852
A76: Wang X.; Liang J.; Rongliang L. | B76: Wang, Xiang (57479223700); Liang, Jingwei (58722424400); Rongliang, Li (59395514200) | C76: 57479223700; 58722424400; 59395514200 | D76: In-site experimental study on the effects of infrared thermal imaging technology on levee leakage detection | E76: 2024 | F76: Scientific Reports | G76: 14 | H76: 1 | I76: 26032 | M76: 10.1038/s41598-024-77383-w | N76: https://www.scopus.com/inward/record.uri?eid=2-s2.0-85208167829&doi=10.1038%2fs41598-024-77383-w&partnerID=40&md5=d5795546b56c65b6ff29a3df2426124a | O76: Excessive seepage significantly affects the stability of levees during flood seasons. Recently, infrared thermal imaging technology has been proposed to detect the seepage leakage of levees for its simplicity, high efficiency and non-contact. However, previous studies mainly focused on theoretical and laboratory tests to verify its effect, which involve many assumptions and simplification. This paper aims to study the practical application effects of infrared thermal imaging technology on levee leakage detection. A typical embankment in Xiangyin County, Hunan Province is selected as the studied area, where a specific point containing water is considered as the potential leakage point. Then, DJI M300RTK UAV equipped with Zenith H20T gimbal is adopted to collect the visible and infrared images of the embankment’s leaking point. The visible and infrared image data collected at different times and at different measurement heights are analyzed to investigate the detection accuracy of infrared thermal imaging technology. Results show that the infrared thermal imaging technology can accurately identify the potential seepage leakage point of levees. Compared with the visible light recognition method, the infrared thermal imaging technology can identify the location and scope of leakage hazards more clearly and accurately at night. During the daytime, infrared detection is less effective than visible light method. Moreover, the measurement altitude between the drone and the target leakage points significantly affects the detection accuracy of infrared thermal imaging technology. © The Author(s) 2024. | P76: Hidden hazard detection; Infrared thermography; Levees; Seepage; Seepage heat transfer | Q76: 2-s2.0-85208167829
A77: Veksler M.; Akkaya K.; Uluagac S. | B77: Veksler, Maryna (57912295300); Akkaya, Kemal (6603154960); Uluagac, Selcuk (22735196300) | C77: 57912295300; 6603154960; 22735196300 | D77: Catch me if you can: Covert Information Leakage from Drones using MAVLink Protocol | E77: 2024 | F77: ACM AsiaCCS 2024 - Proceedings of the 19th ACM Asia Conference on Computer and Communications Security | J77: 912 | K77: 924 | L77: 12 | M77: 10.1145/3634737.3637672 | N77: https://www.scopus.com/inward/record.uri?eid=2-s2.0-85199291347&doi=10.1145%2f3634737.3637672&partnerID=40&md5=3727fa9e100c2574c8d9630df5e22976 | O77: The number of applications of unmanned aerial vehicles (UAVs) (aka drones) is rapidly expanding. However, the wireless and broadcast nature of communications between the drones and their operators (i.e., Ground control station (GCS)) presents a risk for this channel to be exploited by outsiders. Specifically, an attacker can abuse benign communications as a cover to leak sensitive drone data secretly to nearby adversaries within the transmission range of a drone. Therefore, in this paper, we investigate the threat of information leakage through MAVLink, a drone control protocol that is widely used in the majority of drone autopilot systems and is considered a de-facto standard. We show that multiple covert channels can be created in MAVLink by exploiting its lack of security mechanisms, default broadcast messages, and redundant features. We design and implement the novel covert channels on a realistic drone testbed in practical settings and assess their feasibility. Our extensive results demonstrate that attackers can effectively exfiltrate different types of sensitive data from drones with a high throughput via MAVLink-based covert channels in the presence of an active warden at the GCS. Finally, we provide an in-depth analysis of several countermeasures for MAVLink-based covert channels to improve the protocol’s security. To the best of our knowledge, this is the first work exploiting the popular MAVLink protocol for covert communications and demonstrating how it can be manipulated by the adversary for secret communications over commodity drones. © 2024 Copyright held by the owner/author(s). | P77: covert channels; drones; information leakage; MAVLink; unmanned aerial vehicles (UAVs) | Q77: 2-s2.0-85199291347
A78: Schäffer S.; Wolfrum J.; Lueck M.; Osterholz J. | B78: Schäffer, Sebastian (57203091110); Wolfrum, Johannes (7005948340); Lueck, Martin (56897026200); Osterholz, Jens (22980715600) | C78: 57203091110; 7005948340; 56897026200; 22980715600 | D78: Decomposition and vulnerability of CFRP under laser impact with powers of up to 120 kW | E78: 2024 | F78: Proceedings of SPIE - The International Society for Optical Engineering | G78: 13201 | I78: 1320106 | M78: 10.1117/12.3031480 | N78: https://www.scopus.com/inward/record.uri?eid=2-s2.0-85210031693&doi=10.1117%2f12.3031480&partnerID=40&md5=1e7d0efef595cb9dcfd37c94396dc02c | O78: The use of drones and unmanned aerial vehicles (UAVs) poses an increasing aerial threat in both military and civilian sectors. High-energy laser (HEL) systems emerge as a promising way to countermeasure these threats with excellent precision and minimal collateral damage. Considering that UAVs and drones are predominantly constructed from lightweight construction materials like carbon fiber-reinforced polymer (CFRP), investigating the vulnerability of this material class becomes crucial, as it directly impacts the resistance of these platforms against high-energy laser countermeasures. This study presents research on HEL interactions with carbon fiber-reinforced polymer (CFRP) composites, exploring the effects of continuous wave (CW) laser powers of up to 120 kW. We established a laboratory environment that meets the demands of operational safety requirements for laser processing of CFRP including a robot-controlled sample exchange and automatic laser beam shut-off. The interaction of the laser with the composite material was evaluated using high-speed images showing the rapid expansion of a smoke cloud, that contains fragments of fibers and a partially ionized plasma. Experiments reveal a decrease in perforation times with increasing laser power, which can be described by a power law. A detailed examination of the damaged samples, visually and via micro-focused computed X-ray tomography, offers insights into heat affected zones and ablation dynamics. Furthermore, compression after impact (CAI) tests assess the residual strength of the irradiated CFRP panels. A decrease of the compressive strength of a factor of about 2 is observed. The outcomes of this research contribute to the understanding of CFRP behavior under extreme laser conditions, providing valuable knowledge of the dynamic interactions between high-energy lasers and complex composite materials, highlighting potential applications for countermeasures in defense technology. © 2024 SPIE. | P78: CFRP; composite; High-Energy Laser; Laser effects; Laser-impact; Volume-ablation; vulnerability | Q78: 2-s2.0-85210031693
A79: Tufekci B.; Arslan A.; Tunc C.; Morozov K. | B79: Tufekci, Burak (59393088100); Arslan, Atakan (37007594600); Tunc, Cihan (35849159700); Morozov, Kirill (23492776200) | C79: 59393088100; 37007594600; 35849159700; 23492776200 | D79: Enhancing the Security of the MAVLink with Symmetric Authenticated Encryption for Drones | E79: 2024 | F79: 2024 11th International Conference on Internet of Things: Systems, Management and Security, IOTSMS 2024 | J79: 58 | K79: 65 | L79: 7 | M79: 10.1109/IOTSMS62296.2024.10710297 | N79: https://www.scopus.com/inward/record.uri?eid=2-s2.0-85208075442&doi=10.1109%2fIOTSMS62296.2024.10710297&partnerID=40&md5=76380e1984541f2b9d942cb04739f7d3 | O79: The Micro Air Vehicle Link (MAVLink) protocol plays a crucial role in enabling communication between drones and Ground Control Stations (GCS). With the increasing adoption of drones, the security and integrity of MAVLink protocol have also become paramount. This paper delves into the fundamental aspects of MAVLink, highlighting its security challenges and proposing potential solutions to enhance its resilience against cyber threats. The study presents findings on the vulnerabilities of the MAVLink protocol and introduces a novel approach to securing communications on the MAVLink protocol for drones. The paper evaluates different Authenticated Encryption with Associated Data (AEAD) schemes and their impact on the performance of MAVLink, emphasizing the importance of encryption and authentication for ensuring data security. The results demonstrate the efficiency of the Chacha20Poly1305 encryption mechanism in execution time, the AES-OCB3 scheme as the least CPU-intensive, and AES-CCM in terms of memory usage. By adding the AEAD scheme into the MAVLink payload, we not only provide message confidentiality, integrity, and authenticity but also provide MAVLink header integrity to the drone environment. © 2024 IEEE. | P79: cryptography; cybersecurity; Drone; GCS; MAVLink; UAV | Q79: 2-s2.0-85208075442
A80: Ding Y.; Cao Q.; Zhang B.; Li P.; Shi Z. | B80: Ding, Yan (56597197500); Cao, Qingxin (59461558600); Zhang, Bozhi (57204196914); Li, Peilin (57573191200); Shi, Zhongjiao (56669069000) | C80: 56597197500; 59461558600; 57204196914; 57573191200; 56669069000 | D80: Research on multi-view collaborative detection system for UAV swarms based on Pix2Pix framework and BAM attention mechanism | E80: 2024 | F80: Defence Technology | M80: 10.1016/j.dt.2024.11.002 | N80: https://www.scopus.com/inward/record.uri?eid=2-s2.0-85211191138&doi=10.1016%2fj.dt.2024.11.002&partnerID=40&md5=0e2e3a00da7d826d05cc843430ad6e94 | O80: Drone swarm systems, equipped with photoelectric imaging and intelligent target perception, are essential for reconnaissance and strike missions in complex and high-risk environments. They excel in information sharing, anti-jamming capabilities, and combat performance, making them critical for future warfare. However, varied perspectives in collaborative combat scenarios pose challenges to object detection, hindering traditional detection algorithms and reducing accuracy. Limited angle-prior data and sparse samples further complicate detection. This paper presents the Multi-View Collaborative Detection System, which tackles the challenges of multi-view object detection in collaborative combat scenarios. The system is designed to enhance multi-view image generation and detection algorithms, thereby improving the accuracy and efficiency of object detection across varying perspectives. First, an observation model for three-dimensional targets through line-of-sight angle transformation is constructed, and a multi-view image generation algorithm based on the Pix2Pix network is designed. For object detection, YOLOX is utilized, and a deep feature extraction network, BA-RepCSPDarknet, is developed to address challenges related to small target scale and feature extraction challenges. Additionally, a feature fusion network NS-PAFPN is developed to mitigate the issue of deep feature map information loss in UAV images. A visual attention module (BAM) is employed to manage appearance differences under varying angles, while a feature mapping module (DFM) prevents fine-grained feature loss. These advancements lead to the development of BA-YOLOX, a multi-view object detection network model suitable for drone platforms, enhancing accuracy and effectively targeting small objects. © 2024 China Ordnance Society | P80: Attention mechanism; Drone swarm systems; Image generation; Multi-view detection; Pix2Pix framework; Reconnaissance and strike | Q80: 2-s2.0-85211191138
A81: Sharma D.D.; Sarojwal A. | B81: Sharma, Desh Deepak (56924331800); Sarojwal, Atul (57845685800) | C81: 56924331800; 57845685800 | D81: Secure and Resilient Threat Modelling Strategy for Drone Delivery System | E81: 2024 | F81: 2024 IEEE Region 10 Symposium, TENSYMP 2024 | M81: 10.1109/TENSYMP61132.2024.10752205 | N81: https://www.scopus.com/inward/record.uri?eid=2-s2.0-85211951060&doi=10.1109%2fTENSYMP61132.2024.10752205&partnerID=40&md5=35d54c6f5705c9b68a58c675f602f86c | O81: Several unmanned aerial vehicles (UAVs) are used in multi-drone delivery systems to move packages and supplies from a distribution center to specific delivery locations. The key challenges in multi-drone delivery are navigating complex aviation, reliable performance, protection of drones from hacking, ensuring the security of deliveries, gaining public trust, and maintaining privacy. This paper suggests an approach to develop the secured and authentic data structure of drone delivery systems. The paper presents the common threat actors, and identifies different stages of possible threats in drone delivery. The various threat modeling tools are mentioned. This paper proposes the DSA (digital signature algorithm) based secure and resilient algorithm for drone-delivery systems. © 2024 IEEE. | P81: drone delivery cost; DSA; private keys; public keys; threat actors | Q81: 2-s2.0-85211951060
A82: Al-lQubaydhi N.; Alenezi A.; Alanazi T.; Senyor A.; Alanezi N.; Alotaibi B.; Alotaibi M.; Razaque A.; Hariri S. | B82: Al-lQubaydhi, Nader (58876389600); Alenezi, Abdulrahman (57886975400); Alanazi, Turki (58834394900); Senyor, Abdulrahman (57885582800); Alanezi, Naif (57886741900); Alotaibi, Bandar (56823476600); Alotaibi, Munif (56275433000); Razaque, Abdul (25961025600); Hariri, Salim (7005427754) | C82: 58876389600; 57886975400; 58834394900; 57885582800; 57886741900; 56823476600; 56275433000; 25961025600; 7005427754 | D82: Deep learning for unmanned aerial vehicles detection: A review | E82: 2024 | F82: Computer Science Review | G82: 51 | I82: 100614 | M82: 10.1016/j.cosrev.2023.100614 | N82: https://www.scopus.com/inward/record.uri?eid=2-s2.0-85184656031&doi=10.1016%2fj.cosrev.2023.100614&partnerID=40&md5=7df130c44b36740e21b9b30c7ad7908a | O82: As a new type of aerial robotics, drones are easy to use and inexpensive, which has facilitated their acquisition by individuals and organizations. This unequivocal and widespread presence of amateur drones may cause many dangers, such as privacy breaches by reaching sensitive locations of authorities and individuals. In this paper, we summarize the performance-affecting factors and major obstacles to drone use and provide a brief background of deep learning. Then, we summarize the types of UAVs and the related unethical behaviors, safety, privacy, and cybersecurity concerns. Then, we present a comprehensive literature review of current drone detection methods based on deep learning. This area of research has arisen in the last two decades because of the rapid advancement of commercial and recreational drones and their combined risk to the safety of airspace. Various deep learning algorithms and their frameworks with respect to the techniques used to detect drones and their areas of applications are also discussed. Drone detection techniques are classified into four categories: visual, radar, acoustics, and radio frequency-based approaches. The findings of this study prove that deep learning-based detection and classification of drones looks promising despite several challenges. Finally, we provide some recommendations to meet future expectations. © 2023 Elsevier Inc. | P82: Convolutional neural network; Deep learning; Drone detection; Recurrent neural network; Unmanned aerial vehicle | Q82: 2-s2.0-85184656031
A83: Zhang Y. | B83: Zhang, Yue (58873417100) | C83: 58873417100 | D83: Research on Optimization of UAV Communication Network Security Protection Strategy Based on Advanced Encryption Technology | E83: 2024 | F83: Journal of Mobile Multimedia | G83: 13 | H83: 6 | J83: 1379 | K83: 1400 | L83: 21 | M83: 10.13052/jcsm2245-1439.1367 | N83: https://www.scopus.com/inward/record.uri?eid=2-s2.0-85211741117&doi=10.13052%2fjcsm2245-1439.1367&partnerID=40&md5=82e4f22291ab9348181ac0fb93ad0c07 | O83: With the wide application of UAVs in various applications, the security, spectrum, and energy efficiency of their communication networks have become increasingly prominent. This paper proposes a joint optimization strategy based on deep reinforcement learning for drone swarm communication networks. First, a model is constructed that takes into account security threats, spectrum sharing, and energy consumption. Intelligent agents are then trained through deep reinforcement learning to dynamically select the best spectrum allocation and energy strategy to improve spectrum and energy efficiency while maintaining network security. Based on encryption technology, this paper studies resource optimization strategies for UAV security communication in different scenarios. Aiming at the incomplete certainty of multiple eavesdropping positions and the problem of the no-fly zone during UAV flight, a joint optimization algorithm is proposed to optimize UAV trajectory, interference power, and transmission power of ground base stations so as to maximize the minimum average security capacity of the system in the worst case. To solve the problem of the LoS link of UAV being quickly blocked in the city and secondary users easily causing excessive interference to primary users, intelligent reflectors are introduced to assist the UAV in secure communication. IRS can be used to reconfigure channel parameters to control the propagation direction of UAV communication links, enhance the channel quality of the primary link, and weaken the channel quality of eavesdropping links and interference links. Simulation results show that the optimization scheme improves the channel quality of UAV in crowded scenarios, inhibits the eavesdropping effect of eavesdroppers on secondary security users, and reduces the spectrum multiplexing interference of primary users, thus significantly enhancing the security capacity of the system. When the interference power of UAVs is increased, the value and growth rate of the security capacity of security users are significantly increased. The increase is 20%. Through a large number of simulation experiments, it has been proved that this method has excellent performance in improving communication security, spectrum utilization, and energy efficiency and has obvious advantages over the traditional baseline and average allocation DQN-wrap method. © 2024 River Publishers. | P83: communication security optimization; encryption technology; network security; spectrum energy efficiency optimization; UAV | Q83: 2-s2.0-85211741117
A84: Sophia S.; Paulraj G.J.L.; Jebadurai I.J. | B84: Sophia, S. (57871863800); Paulraj, Getzi Jeba Leelipushpam (57194531541); Jebadurai, Immanuel Johnraja (59337191700) | C84: 57871863800; 57194531541; 59337191700 | D84: Internet of Drones Security and Privacy | E84: 2024 | F84: Cyber Space and Outer Space Security | J84: 197 | K84: 215 | L84: 18 | N84: https://www.scopus.com/inward/record.uri?eid=2-s2.0-85201577894&partnerID=40&md5=02d3410fc148daa2e09e829ee063cdbe | O84: The usage of unmanned aerial vehicles has increased in the recent past in various applications due to their ability to transport objects, take images, and feed live videos. Incorporated with the Internet of Things, the unmanned aerial vehicle has been renamed the Internet of Drones. Applications of the Internet of Drones include traffic surveillance, defense, agriculture crops monitoring, cinematography, underwater purposes, healthcare, logistics, commercial aids, GIS (geographic information system) mapping, environmental management, smart cities, disaster management, search and rescue operations, and various military applications. The decentralized network and management architecture of drones are connected and controlled to form the Internet of Drones. In the Internet of Drone environment, a network made up of numerous drones transmits and receives data from one another. A lack of security makes it possible for an attacker to exploit this vulnerability and manipulate or abuse sensor inputs or functions, or deactivate them to launch cyber-attacks and produce unpleasant failsafe measures. The possibility and frequency of these attacks are very high, which affects the privacy, confidentiality, availability, integrity, and trust of drone data. Thus, the security and privacy threats have to be addressed and it is necessary to take preventive and protective countermeasures. This chapter surveys the possible cyber-attacks and the security against such attacks. Also, it comes up with new technologies and techniques to overcome cyber-attacks on the Internet of Drones. Finally, it guides future research to help in the identification of the most recent Internet of Drone research opportunities. © 2024 River Publishers. All rights reserved. | Q84: 2-s2.0-85201577894
